Workbook
Name ActLab: #REF!
Name ActLab0: #REF!
Name ActMap: #REF!
Name actProd: #REF!
Name AEEI: #REF!
Name BridgeFileName: #REF!
Name CommAgg: #REF!
Name CommElas: #REF!
Name CommLab: #REF!
Name CommLab0: #REF!
Name CommMap: #REF!
Name depr: #REF!
Name Description: #REF!
Name Dyntab: #REF!
Name EMICO2: #REF!
Name escale: #REF!
Name EXR: #REF!
Name fdComm: #REF!
Name fdCommMap: #REF!
Name GDDebt0: #REF!
Name GDPMod: #REF!
Name GDPScen: #REF!
Name GFDebt0: #REF!
Name hhElas: defPar!$B$12:$C$35
Name ifEnglish: #REF!
Name inscale: #REF!
Name KSAMA0: #REF!
Name Labvol: #REF!
Name Lang: #REF!
Name miscElas: defPar!#REF!
Name NRGPrice: #REF!
Name PFDebt0: #REF!
Name Pop: #REF!
Name popScen: #REF!
Name prodElas: #REF!
Name pscale: #REF!
Name RGDDebt0: #REF!
Name RGFDebt0: #REF!
Name RoR0: #REF!
Name RPFDebt0: #REF!
Name SAM0: #REF!
Name SAMFileName: #REF!
Name SAMLab: #REF!
Name SamLab0: #REF!
Name samMap: #REF!
Name SAMVAL: #REF!
Name scenFileName: #REF!
Name timeScen: #REF!
Name wDir: #REF!

Sheet Dictionary
A1: Activities | D1: Commodities | H1: Factors | K1: Households | N1: Institutions | Q1: Taxes
A2: a-crp | B2: Crop Production | D2: c-crp | E2: Crop Production | H2: f-Land | I2: Land | K2: h-Dec1 | L2: Quintile 1 (poorest) | N2: e-ent | O2: Enterprises | Q2: t-Land | R2: =+I2&" factor tax" -> Land factor tax | T2: 1 | U2: pdr | V2: Paddy rice
A3: a-lvs | B3: Livestock production | D3: c-lvs | E3: Livestock production | H3: f-FrSkl | I3: Skilled formal Labor | K3: h-Dec2 | L3: Quintile 2 | N3: g-govt | O3: Government | Q3: t-labSk | R3: =+I3&" factor tax" -> Skilled formal Labor factor tax | T3: 2 | U3: wht | V3: Wheat
A4: a-frs | B4: Forestry | D4: c-frs | E4: Forestry | H4: f-FrNsk | I4: Unskilled formal Labor | K4: h-Dec3 | L4: Quintile 3 | N4: w-ww_world | O4: Rest of the World | Q4: t-labUs | R4: =+I4&" factor tax" -> Unskilled formal Labor factor tax | T4: 3 | U4: gro | V4: Cereal grains nec
A5: a-coa | B5: Coal | D5: c-coa | E5: Coal | H5: f-InNsk | I5: Unskilled Formal Labor | K5: h-Dec4 | L5: Quintile 4 | Q5: t-Capital | R5: =+I6&" factor tax" -> Capital factor tax | T5: 4 | U5: v_f | V5: Vegetables, fruit, nuts
A6: a-oil | B6: Oil | D6: c-oil | E6: Oil | H6: f-Capital | I6: Capital | K6: h-Dec5 | L6: Quintile 5 | Q6: t-NatlRes | R6: =+I7&" factor tax" -> Natural Resources factor tax | T6: 5 | U6: osd | V6: Oil seeds
A7: a-gas | B7: Gas | D7: c-gas | E7: Gas | H7: f-NatlRes | I7: Natural Resources | K7: h-Dec6 | L7: Quintile 6 | Q7: t-tmm_world | R7: Tariffs | T7: 6 | U7: c_b | V7: Sugar cane, sugar beet
A8: a-oxt | B8: Other Extraction | D8: c-oxt | E8: Other Extraction | K8: h-Dec7 | L8: Quintile 7 | Q8: t-PRODTAX | R8: Production tax | T8: 7 | U8: pfb | V8: Plant-based fibers
A9: a-fod | B9: Food products | D9: c-fod | E9: Food products | K9: h-Dec8 | L9: Quintile 8 | Q9: t-DIRTAX | R9: Diret tax | T9: 8 | U9: ocr | V9: Crops nec
A10: a-b_t | B10: Beverages and tobacco products | D10: c-b_t | E10: Beverages and tobacco products | K10: h-Dec9 | L10: Quintile 9 | Q10: t-tss | R10: Excise tax | T10: 9 | U10: ctl | V10: Bovine cattle, sheep and goats, horses
A11: a-tex | B11: Textiles | D11: c-tex | E11: Textiles | K11: h-DecX | L11: Quintile 10 (richest) | Q11: t-vat | R11: Value added tax | T11: 10 | U11: oap | V11: Animal products nec
A12: a-wod | B12: Wood products and paper | D12: c-wod | E12: Wood products and paper | T12: 11 | U12: rmk | V12: Raw milk
A13: a-p_c | B13: Petroleum, coal products | D13: c-p_c | E13: Petroleum, coal products | T13: 12 | U13: wol | V13: Wool, silk-worm cocoons
A14: a-chm | B14: Chemical products | D14: c-chm | E14: Chemical products | T14: 13 | U14: frs | V14: Forestry
A15: a-bph | B15: Basic pharmaceutical products | D15: c-bph | E15: Basic pharmaceutical products | T15: 14 | U15: fsh | V15: Fishing
A16: a-nmm | B16: Mineral products nec | D16: c-nmm | E16: Mineral products nec | T16: 15 | U16: coa
A17: a-i_s | B17: Ferrous metals | D17: c-i_s | E17: Ferrous metals | T17: 16 | U17: oil
A18: a-nfm | B18: Metals nec | D18: c-nfm | E18: Metals nec | T18: 17 | U18: gas
A19: a-fmp | B19: Metal products | D19: c-fmp | E19: Metal products | T19: 18 | U19: oxt
A20: a-ele | B20: Electrical equipment, electronics, machinery and equipment | D20: c-ele | E20: Electrical equipment, electronics, machinery and equipment | T20: 19 | U20: cmt
A21: a-mvh | B21: Motor vehicles and parts | D21: c-mvh | E21: Motor vehicles and parts | T21: 20 | U21: omt
A22: a-omf | B22: Manufactures nec | D22: c-omf | E22: Manufactures nec | T22: 21 | U22: vol
A23: a-TnD | B23: Electricity transmission and distribution | D23: c-TnD | E23: Electricity transmission and distribution | T23: 22 | U23: mil
A24: a-NuclearP | B24: Nuvlear Power | D24: c-ely | E24: Electricity | T24: 23 | U24: pcr
A25: a-CoalP | B25: Coal Power | D25: c-gdt | E25: Gas distribution | T25: 24 | U25: sgr
A26: a-GasP | B26: Gas Power | D26: c-wtr | E26: Water, waste and utilities | T26: 25 | U26: ofd
A27: a-WindP | B27: Wind Power | D27: c-cns | E27: Construction | T27: 26 | U27: b_t
... A40: a-ofi | B40: Financial services nec | D40: c-hht | E40: Human health and social work activities | T40: 39 | U40: fmp
A41: a-ins | B41: Insurance (formerly isr) | T41: 40 | U41: ele
A42: a-osr | B42: Business services nec | T42: 41 | U42: eeq
A43: a-osg | B43: Public Administration and defense | T43: 42 | U43: ome
A44: a-edu | B44: Education | T44: 43 | U44: mvh
A45: a-hht | B45: Human health and social work activities | T45: 44 | U45: otn
T46: 45 | U46: omf
T47: 46 | U47: ely
T48: 47 | U48: gdt
T49: 48 | U49: wtr
T50: 49 | U50: cns
T51: 50 | U51: trd
T52: 51 | U52: afs
T53: 52 | U53: otp
T54: 53 | U54: wtp
T55: 54 | U55: atp
T56: 55 | U56: whs
T57: 56 | U57: cmn
... T66: 65 | U66: dwe

Sheet Layout
A1: LAYOUT
A3: Comment | B3: Data Type | C3: Name | D3: Location | E3: Row dimension | F3: Column dimension | G3: Total dimension
E4: rdim | F4: cdim | G4: dim
A5: Maping from activities to GTAP | B5: set | C5: mapaGTAP | D5: =IF(B5="dset","Sets!"&HLOOKUP(C5,sets!$B$2:$WY$3,2,)&6,IF(B5="set","Maps!"&HLOOKUP(C5,maps!$A$2:$YR$3,2,)&6)) -> Maps!A6 | E5: 2
A6: Maping from products to GTAP | B6: set | C6: mapcGTAP | D6: =IF(B6="dset","Sets!"&HLOOKUP(C6,sets!$B$2:$WY$3,2,)&6,IF(B6="set","Maps!"&HLOOKUP(C6,maps!$A$2:$YR$3,2,)&6)) -> Maps!D6 | E6: 2
A7: All accounts (plus nests) | B7: dset | C7: is | D7: =IF(B7="dset","Sets!"&HLOOKUP(C7,sets!$B$2:$WY$3,2,)&6,IF(B7="set","Maps!"&HLOOKUP(C7,maps!$A$2:$YR$3,2,)&6)) -> Sets!B6 | E7: 1
A8: Energy products | B8: dset | C8: e | D8: =IF(B8="dset","Sets!"&HLOOKUP(C8,sets!$B$2:$WY$3,2,)&6,IF(B8="set","Maps!"&HLOOKUP(C8,maps!$A$2:$YR$3,2,)&6)) -> Sets!G6 | E8: 1
A9: Debt account | B9: dset | C9: debt | D9: =IF(B9="dset","Sets!"&HLOOKUP(C9,sets!$B$2:$WY$3,2,)&6,IF(B9="set","Maps!"&HLOOKUP(C9,maps!$A$2:$YR$3,2,)&6)) -> Sets!S6 | E9: 1
A10: Labor accounts | B10: dset | C10: l | D10: =IF(B10="dset","Sets!"&HLOOKUP(C10,sets!$B$2:$WY$3,2,)&6,IF(B10="set","Maps!"&HLOOKUP(C10,maps!$A$2:$YR$3,2,)&6)) -> Sets!H6 | E10: 1
A11: Capital account | B11: dset | C11: cap | D11: =IF(B11="dset","Sets!"&HLOOKUP(C11,sets!$B$2:$WY$3,2,)&6,IF(B11="set","Maps!"&HLOOKUP(C11,maps!$A$2:$YR$3,2,)&6)) -> Sets!I6 | E11: 1
A12: Land accounts | B12: dset | C12: lnd | D12: =IF(B12="dset","Sets!"&HLOOKUP(C12,sets!$B$2:$WY$3,2,)&6,IF(B12="set","Maps!"&HLOOKUP(C12,maps!$A$2:$YR$3,2,)&6)) -> Sets!J6 | E12: 1
A13: Natural ressources | B13: dset | C13: natres | D13: =IF(B13="dset","Sets!"&HLOOKUP(C13,sets!$B$2:$WY$3,2,)&6,IF(B13="set","Maps!"&HLOOKUP(C13,maps!$A$2:$YR$3,2,)&6)) -> Sets!K6 | E13: 1
A14: All investment account | B14: dset | C14: inv | D14: =IF(B14="dset","Sets!"&HLOOKUP(C14,sets!$B$2:$WY$3,2,)&6,IF(B14="set","Maps!"&HLOOKUP(C14,maps!$A$2:$YR$3,2,)&6)) -> Sets!L6 | E14: 1
A15: Government investment account | B15: dset | C15: ginv | D15: =IF(B15="dset","Sets!"&HLOOKUP(C15,sets!$B$2:$WY$3,2,)&6,IF(B15="set","Maps!"&HLOOKUP(C15,maps!$A$2:$YR$3,2,)&6)) -> Sets!M6 | E15: 1
A16: Adaptive investment account | B16: dset | C16: adpinv | D16: =IF(B16="dset","Sets!"&HLOOKUP(C16,sets!$B$2:$WY$3,2,)&6,IF(B16="set","Maps!"&HLOOKUP(C16,maps!$A$2:$YR$3,2,)&6)) -> Sets!N6 | E16: 1
... A23: Aggregation from proto to final SAM | B23: set | C23: mapis | D23: =IF(B23="dset","Sets!"&HLOOKUP(C23,sets!$B$2:$WY$3,2,)&6,IF(B23="set","Maps!"&HLOOKUP(C23,maps!$A$2:$YR$3,2,)&6)) -> Maps!G6 | E23: 2
A24: Demand bundle composition | B24: par | C24: mapkNestShr | D24: mapk!B5 | E24: 1 | F24: 1
A25: Substitutional elasticities in demand nests | B25: par | C25: sigmacNest0 | D25: mapk!C2 | F25: 1
A26: Map from aggregated to single sectors | B26: set | C26: mapaagr | D26: =IF(B26="dset","Sets!"&HLOOKUP(C26,sets!$B$2:$WY$3,2,)&6,IF(B26="set","Maps!"&HLOOKUP(C26,maps!$A$2:$YR$3,2,)&6)) -> Maps!M6 | E26: 2
A27: Production nesting | B27: par | C27: pnest | D27: pnest!B6 | E27: 2 | F27: 1
A28: Substitution elasticities for production nests | B28: par | C28: subselas | D28: pnest!C2 | E28: 1 | F28: 1
A29: Factor market nestings | B29: par | C29: fmNest | D29: fmNest!B9
A30: Parameters for factor market nests | B30: par | C30: fmNestPar | D30: fmNest!B2
A31: Age cohotrs | B31: dset | C31: cohorts | D31: =IF(B31="dset","Sets!"&HLOOKUP(C31,sets!$B$2:$WY$3,2,)&6,IF(B31="set","Maps!"&HLOOKUP(C31,maps!$A$2:$YR$3,2,)&6)) -> Sets!Q6 | E31: 1
A32: Initial SAM | B32: par | C32: SAM0 | D32: SAM!A1 | E32: 1 | F32: 1
A33: default parameter values | B33: par | C33: defPar | D33: defPar!B2 | E33: 1
A34: exceptions in activity parameters | B34: par | C34: actPar | D34: actPar!A1 | E34: 1 | F34: 2
A35: exceptions in commodity parameters | B35: par | C35: comPar | D35: comPar!A1 | E35: 1 | F35: 1
A36: exceptions in HH parameters | B36: par | C36: hohPar | D36: hohPar!B9 | E36: 1 | F36: 2
A37: exceptions inother parameters | B37: par | C37: othpar | D37: othPar!A1 | E37: 1 | F37: 1
A38: labor quantities for initial SAM, aggregated to model SAM dimensions in base.inc | B38: par | C38: labor0 | D38: labor!B1 | E38: 1 | F38: 1
A39: Official Emission inventory - combustion | B39: par | C39: emiInventory_OFF | D39: emiinv!A2 | E39: 1 | F39: 1
A40: Official Emission inventory - Process | B40: par | C40: emiInventoryXP_OFF | D40: emiinv!A12 | E40: 1 | F40: 1
A41: Power mix | B41: par | C41: powerMix | D41: powerMix!A1 | E41: 2 | F41: 1
A42: GHG mitigation | B42: par | C42: GHGMitigation | D42: GHGMitigation!A1 | E42: 2 | F42: 1
A43: Energy projections | B43: par | C43: energyProj | D43: Energy!A1 | E43: 3 | F43: 1
A44: Nutrient contents | B44: par | C44: nutCont | D44: Nutrients!A1 | E44: 1 | F44: 1
A45: Points on Marginal Abatement Cost Curves | B45: par | C45: macc | D45: macc!A1 | E45: 1 | F45: 1
... A48: Factor supply distribution across institutions | B48: par | C48: xfmSupDistrInst | D48: hohPar!B15 | E48: 2 | F48: 1
A49: endogenous tech change parameters | B49: par | C49: EnTPar | D49: EnTech!G5 | E49: 1
A50: stepping on toes effect | B50: par | C50: PhiRDtoes | D50: EnTech!A5 | E50: 1
A51: supernormal growth of sectors | B51: par | C51: Supfgrowth | D51: EnTech!D5 | E51: 1

Sheet MACC
B1: 0 | C1: 1 | D1: 5 | E1: 10 | F1: 50 | G1: 100 | H1: 360 | I1: 380
A2: rest | B2: 1e-10 | C2: 1e-06 | D2: 0.05 | E2: 0.1 | F2: 0.2 | G2: 0.5 | H2: 0.6 | I2: 1
A3: a-nmm | B3: 1e-10 | C3: 1e-06 | D3: 0.0001 | F3: 0.9 | G3: 0.95 | H3: 0.99 | I3: 1
A4: a-bph | B4: 1e-10 | C4: 1e-06 | D4: 0.0001 | F4: 0.75 | G4: 0.9 | H4: 0.95 | I4: 1
A5: a-chm | B5: 1e-10 | C5: 1e-06 | D5: 0.0001 | F5: 0.75 | G5: 0.9 | H5: 0.95 | I5: 1
A6: a-ele | B6: 1e-10 | C6: 1e-06 | D6: 0.0001 | F6: 0.2 | G6: 0.3 | H6: 0.4 | I6: 1
A7: a-wtr | B7: 1e-10 | C7: 1e-06 | D7: 0.0001 | F7: 0.2 | G7: 0.3 | H7: 0.4 | I7: 1
A8: a-oap | B8: 1e-10 | C8: 1e-06 | D8: 0.0001 | G8: 0.07 | H8: 0.08 | I8: 1
A9: a-wol | B9: 1e-10 | C9: 1e-06 | D9: 0.0001 | G9: 0.07 | H9: 0.08 | I9: 1
A10: a-ctl | B10: 1e-10 | C10: 1e-06 | D10: 0.0001 | G10: 0.07 | H10: 0.08 | I10: 1
A11: a-ctlRais | B11: 1e-10 | C11: 1e-06 | D11: 0.0001 | G11: 0.07 | H11: 0.08 | I11: 1
A12: a-rmk | B12: 1e-10 | C12: 1e-06 | D12: 0.0001 | G12: 0.07 | H12: 0.08 | I12: 1
A13: a-pdr | B13: 1e-10 | C13: 1e-06 | D13: 0.0001 | G13: 0.16 | H13: 0.17 | I13: 1
A14: a-wht | B14: 1e-10 | C14: 1e-06 | D14: 0.0001 | G14: 0.1 | H14: 0.12 | I14: 1
A15: a-gro | B15: 1e-10 | C15: 1e-06 | D15: 0.0001 | G15: 0.1 | H15: 0.12 | I15: 1
A16: a-osd | B16: 1e-10 | C16: 1e-06 | D16: 0.0001 | G16: 0.1 | H16: 0.12 | I16: 1
A17: a-v_f | B17: 1e-10 | C17: 1e-06 | D17: 0.0001 | G17: 0.1 | H17: 0.12 | I17: 1
A18: a-pbf | B18: 1e-10 | C18: 1e-06 | D18: 0.0001 | G18: 0.1 | H18: 0.12 | I18: 1
A19: a-c_b | B19: 1e-10 | C19: 1e-06 | D19: 0.0001 | G19: 0.1 | H19: 0.12 | I19: 1
A20: a-ocr | B20: 1e-10 | C20: 1e-06 | D20: 0.0001 | G20: 0.1 | H20: 0.12 | I20: 1

Sheet sets
B1: Model Specific Sets
B2: =+B5 -> is | C2: =+C5 -> 0 | D2: =+D5 -> aagr | G2: =+G5 -> e | H2: =+H5 -> l | I2: =+I5 -> cap | J2: =+J5 -> lnd | K2: =+K5 -> natres | L2: =+L5 -> inv | M2: =+M5 -> ginv | N2: =+N5 -> adpinv | ... Q2: =+Q5 -> cohorts | S2: =+S5 -> debt | T2: =+T5 -> nrgfac | U2: =+U5 -> gtapVersion | V2: =+V5 -> BaseYear
B3: =SUBSTITUTE(ADDRESS(1,COLUMN(),4),1,) -> B | C3: =SUBSTITUTE(ADDRESS(1,COLUMN(),4),1,) -> C | D3: =SUBSTITUTE(ADDRESS(1,COLUMN(),4),"1","") -> D | G3: =SUBSTITUTE(ADDRESS(1,COLUMN(),4),"1","") -> G | H3: =SUBSTITUTE(ADDRESS(1,COLUMN(),4),"1","") -> H | I3: =SUBSTITUTE(ADDRESS(1,COLUMN(),4),"1","") -> I | J3: =SUBSTITUTE(ADDRESS(1,COLUMN(),4),"1","") -> J | K3: =SUBSTITUTE(ADDRESS(1,COLUMN(),4),"1","") -> K | L3: =SUBSTITUTE(ADDRESS(1,COLUMN(),4),"1","") -> L | M3: =SUBSTITUTE(ADDRESS(1,COLUMN(),4),"1","") -> M | N3: =SUBSTITUTE(ADDRESS(1,COLUMN(),4),"1","") -> N | ... Q3: =SUBSTITUTE(ADDRESS(1,COLUMN(),4),"1","") -> Q | S3: =SUBSTITUTE(ADDRESS(1,COLUMN(),4),"1","") -> S | T3: =SUBSTITUTE(ADDRESS(1,COLUMN(),4),"1","") -> T | U3: =SUBSTITUTE(ADDRESS(1,COLUMN(),4),"1","") -> U | V3: =SUBSTITUTE(ADDRESS(1,COLUMN(),4),"1","") -> V
B5: is | D5: aagr | G5: e | H5: l | I5: cap | J5: lnd | K5: natres | L5: inv | M5: ginv | N5: adpinv | O5: stb | P5: row | Q5: cohorts | S5: debt | T5: nrgfac | U5: gtapVersion | V5: BaseYear
B6: a-pdr | C6: Paddy rice production | D6: agri | E6: agriculture | G6: c-p_c | H6: f-tech_aspros | I6: f-Capital | J6: f-Land | K6: f-NatlRes | L6: i-CGDS | M6: i-ginv | P6: w-ww_world | Q6: PLT15 | R6: Age lt 15 | S6: debt | T6: ener | U6: gtapData11c | V6: 2017
B7: a-wht | C7: Wheat production | D7: allIndustry | E7: All industry | G7: c-coa | H7: f-clerks | J7: f-AEZ1 | Q7: P1564 | R7: Age 15-64
B8: a-gro | C8: Coarse grains production | D8: mine | E8: mining | G8: c-oil | H8: f-service_shop | J8: f-AEZ2 | Q8: P65UP | R8: Age gt 64
B9: a-v_f | C9: Fruits and vegetable production | D9: manu | E9: manufacturing | G9: c-gas | H9: f-off_mgr_pros | J9: f-AEZ3 | Q9: PTOTL | R9: All ages
B10: a-osd | C10: Oilseeds production | D10: hema | E10: heavy manufacturin | G10: c-ely | H10: f-ag_othlowsk | J10: f-AEZ4
B11: a-c_b | C11: Sugar cane and beet production | D11: ener | E11: energy | H11: f-m_tech_aspros | J11: f-AEZ5
B12: a-pfb | C12: Production of plant based fibres | D12: cons | E12: construction | H12: f-m_clerks | J12: f-AEZ6
B13: a-ocr | C13: Production of other crops | D13: allServices | E13: All services | H13: f-m_service_shop | J13: f-AEZ7
B14: a-ctl | C14: Ruminants for meat | D14: wast | E14: Waste and water | H14: f-m_off_mgr_pros | J14: f-AEZ8
B15: a-ctlRais | C15: Cattle raising | D15: trad | E15: Trade | H15: f-m_ag_othlowsk | J15: f-AEZ9
B16: a-oap | C16: Other animal production | D16: tran | E16: Transport | H16: f-f_tech_aspros | J16: f-AEZ10
B17: a-rmk | C17: Raw milk production | D17: serv | E17: services | H17: f-f_clerks | J17: f-AEZ11
B18: a-wol | C18: Wool production | D18: Taxes | E18: Taxes | H18: f-f_service_shop | J18: f-AEZ12
B19: a-frs | C19: Forestry production | D19: GrDomProd | E19: GDP | H19: f-f_off_mgr_pros | J19: f-AEZ13
B20: a-fsh | C20: Fisheries | D20: GrDomProdGro | E20: GDP Growth | H20: f-f_ag_othlowsk | J20: f-AEZ14
B21: a-coa | C21: Coal extraction | H21: f-m_skl | J21: f-AEZ15
B22: a-oil | C22: Oil extraction | H22: f-f_skl | J22: f-AEZ16
B23: a-gas | C23: Gas extraction | H23: f-m_nsk | J23: f-AEZ17
B24: a-oxt | C24: Other extraction | H24: f-f_nsk | J24: f-AEZ18
B25: a-cmt | C25: Cattle meat production | J25: f-water
B26: a-omt | C26: Other meat production
B27: a-vol | C27: Vegetable oil and cake production
B28: a-mil | C28: Dairies
B29: a-pcr | C29: Rice processing
B30: a-sgr | C30: Sugar processing
B31: a-ofd | C31: Other food industries
B32: a-b_t | C32: Beverages and tobacco production
B33: a-tex | C33: Textile production
B34: a-wap | C34: Production of wearing apparel
B35: a-lea | C35: Production of leather
B36: a-lum | C36: Production of wood products
B37: a-ppp | C37: Paper and publishing industries
... B267: f-top | C267: Total production bundle
B268: na
B269: GHGs
B270: Acid
B271: TOFP
B272: PMTn
B273: PMTF
B274: AirT

Sheet maps
A1: Maps
A2: =+A5 -> mapaGTAP | B2: =+B5 -> 0 | C2: =+C5 -> 0 | D2: =+D5 -> mapcGTAP | E2: =+E5 -> 0 | F2: =+F5 -> 0 | G2: =+G5 -> mapis | H2: =+H5 -> 0 | ... K2: =+K5 -> 0 | M2: =+M5 -> mapaagr | N2: =+N5 -> 0 | O2: =+O5 -> 0 | P2: =+P5 -> 0 | Q2: =+Q5 -> 0 | R2: =+R5 -> 0 | S2: =+S5 -> 0 | T2: =+T5 -> 0 | ... Y2: =+Y5 -> 0
A3: =+SUBSTITUTE(ADDRESS(1,COLUMN(),4),"1","") -> A | B3: =+SUBSTITUTE(ADDRESS(1,COLUMN(),4),"1","") -> B | C3: =+SUBSTITUTE(ADDRESS(1,COLUMN(),4),"1","") -> C | D3: =+SUBSTITUTE(ADDRESS(1,COLUMN(),4),"1","") -> D | E3: =+SUBSTITUTE(ADDRESS(1,COLUMN(),4),"1","") -> E | F3: =+SUBSTITUTE(ADDRESS(1,COLUMN(),4),"1","") -> F | G3: =+SUBSTITUTE(ADDRESS(1,COLUMN(),4),"1","") -> G | H3: =+SUBSTITUTE(ADDRESS(1,COLUMN(),4),"1","") -> H | ... K3: =+SUBSTITUTE(ADDRESS(1,COLUMN(),4),"1","") -> K | M3: =+SUBSTITUTE(ADDRESS(1,COLUMN(),4),"1","") -> M | N3: =+SUBSTITUTE(ADDRESS(1,COLUMN(),4),"1","") -> N | O3: =+SUBSTITUTE(ADDRESS(1,COLUMN(),4),"1","") -> O | P3: =+SUBSTITUTE(ADDRESS(1,COLUMN(),4),"1","") -> P | Q3: =+SUBSTITUTE(ADDRESS(1,COLUMN(),4),"1","") -> Q | R3: =+SUBSTITUTE(ADDRESS(1,COLUMN(),4),"1","") -> R | S3: =+SUBSTITUTE(ADDRESS(1,COLUMN(),4),"1","") -> S | T3: =+SUBSTITUTE(ADDRESS(1,COLUMN(),4),"1","") -> T | ... Y3: =+SUBSTITUTE(ADDRESS(1,COLUMN(),4),"1","") -> Y
M4: h+f
A5: mapaGTAP | D5: mapcGTAP | G5: mapis | J5: maptax | M5: mapaagr
A6: pdr | B6: a-pdr_0 | D6: pdr | E6: c-pdr_0 | G6: a-pdr_0 | H6: a-pdr | J6: dtx | K6: t-DIRTAX | M6: agri | N6: a-pdr
A7: wht | B7: a-wht_0 | D7: wht | E7: c-wht_0 | G7: a-wht_0 | H7: a-wht | J7: ptx | K7: t-PRODTAX | M7: agri | N7: a-wht
A8: gro | B8: a-gro_0 | D8: gro | E8: c-gro_0 | G8: a-gro_0 | H8: a-gro | J8: stx | K8: t-stx | M8: agri | N8: a-gro
A9: v_f | B9: a-v_f_0 | D9: v_f | E9: c-v_f_0 | G9: a-v_f_0 | H9: a-v_f | J9: mtx | K9: t-imp | M9: agri | N9: a-v_f
A10: osd | B10: a-osd_0 | D10: osd | E10: c-osd_0 | G10: a-osd_0 | H10: a-osd | J10: vat | K10: na | M10: agri | N10: a-osd
A11: c_b | B11: a-c_b_0 | D11: c_b | E11: c-c_b_0 | G11: a-c_b_0 | H11: a-c_b | J11: ctx | K11: na | M11: agri | N11: a-c_b
A12: pfb | B12: a-pfb_0 | D12: pfb | E12: c-pfb_0 | G12: a-pfb_0 | H12: a-pfb | J12: psb | K12: na | M12: agri | N12: a-pfb
A13: ocr | B13: a-ocr_0 | D13: ocr | E13: c-ocr_0 | G13: a-ocr_0 | H13: a-ocr | J13: etx | K13: t-exp | M13: agri | N13: a-ocr
A14: ctl | B14: a-ctl_0 | D14: ctl | E14: c-ctl_0 | G14: a-ctl_0 | H14: a-ctl | J14: ssb | K14: na | M14: agri | N14: a-ctl
A15: ctl | B15: a-ctlRais_0 | D15: ctl | E15: c-ctlRais_0 | G15: a-ctlRais_0 | H15: a-ctlRais | M15: agri | N15: a-ctlRais
A16: oap | B16: a-oap_0 | D16: oap | E16: c-oap_0 | G16: a-oap_0 | H16: a-oap | M16: agri | N16: a-oap
A17: rmk | B17: a-rmk_0 | D17: rmk | E17: c-rmk_0 | G17: a-rmk_0 | H17: a-rmk | M17: agri | N17: a-rmk
A18: rmk | B18: a-ctlRais_0 | D18: rmk | E18: c-ctlRais_0 | G18: a-wol_0 | H18: a-wol | M18: agri | N18: a-wol
A19: wol | B19: a-wol_0 | D19: wol | E19: c-wol_0 | G19: a-frs_0 | H19: a-frs | M19: agri | N19: a-frs
A20: frs | B20: a-frs_0 | D20: frs | E20: c-frs_0 | G20: a-fsh_0 | H20: a-fsh | M20: agri | N20: a-fsh
A21: fsh | B21: a-fsh_0 | D21: fsh | E21: c-fsh_0 | G21: a-coa_0 | H21: a-coa | M21: mine | N21: a-oil
A22: coa | B22: a-coa_0 | D22: coa | E22: c-coa_0 | G22: a-oil_0 | H22: a-oil | M22: mine | N22: a-gas
A23: oil | B23: a-oil_0 | D23: oil | E23: c-oil_0 | G23: a-gas_0 | H23: a-gas | M23: mine | N23: a-coa
A24: gas | B24: a-gas_0 | D24: gas | E24: c-gas_0 | G24: a-oxt_0 | H24: a-oxt | M24: mine | N24: a-oxt
A25: oxt | B25: a-oxt_0 | D25: oxt | E25: c-oxt_0 | G25: a-cmt_0 | H25: a-cmt | M25: manu | N25: a-cmt
A26: cmt | B26: a-cmt_0 | D26: cmt | E26: c-cmt_0 | G26: a-omt_0 | H26: a-omt | M26: manu | N26: a-omt
... A84: dwe | B84: a-dwe_0 | D84: dwe | E84: c-dwe_0 | G84: a-macc_0 | H84: a-macc | M84: serv | N84: a-macc
G85: a-care_0 | H85: a-care | M85: serv | N85: a-care
G86: c-pdr_0 | H86: c-pdr
G87: c-wht_0 | H87: c-wht
G88: c-gro_0 | H88: c-gro
G89: c-v_f_0 | H89: c-v_f
G90: c-osd_0 | H90: c-osd
G91: c-c_b_0 | H91: c-c_b
G92: c-pfb_0 | H92: c-pfb
G93: c-ocr_0 | H93: c-ocr
G94: c-ctl_0 | H94: c-ctl
G95: c-ctlRais_0 | H95: c-ctlRais
G96: c-oap_0 | H96: c-oap
G97: c-rmk_0 | H97: c-rmk
... G262: w-ww_world_0 | H262: w-ww_world

Sheet PowerMix
C1: 2017 | D1: 2018 | E1: 2019 | F1: 2020 | G1: 2021 | H1: 2022 | I1: 2023 | J1: 2024 | K1: 2025 | L1: 2026 | M1: 2027 | N1: 2028 | O1: 2029 | P1: 2030 | Q1: 2031 | R1: 2032 | S1: 2033 | T1: 2034 | U1: 2035 | V1: 2036 | W1: 2037 | X1: 2038 | Y1: 2039 | Z1: 2040 | AA1: 2041 | AB1: 2042 | AC1: 2043 | AD1: 2044 | AE1: 2045 | AF1: 2046 | AG1: 2047 | AH1: 2048 | AI1: 2049 | AJ1: 2050 | AK1: 2051 | AL1: 2052 | AM1: 2053 | AN1: 2054 | AO1: 2055 | AP1: 2056 | AQ1: 2057 | AR1: 2058 | AS1: 2059 | AT1: 2060 | AU1: 2061 | AV1: 2062 | AW1: 2063 | AX1: 2064 | AY1: 2065 | AZ1: 2066 | BA1: 2067 | BB1: 2068 | BC1: 2069 | BD1: 2070 | BE1: 2071 | BF1: 2072 | BG1: 2073 | BH1: 2074 | BI1: 2075 | BJ1: 2076 | BK1: 2077 | BL1: 2078 | BM1: 2079 | BN1: 2080 | BO1: 2081 | BP1: 2082 | BQ1: 2083 | BR1: 2084 | BS1: 2085 | BT1: 2086 | BU1: 2087 | BV1: 2088 | BW1: 2089 | BX1: 2090 | BY1: 2091 | BZ1: 2092 | CA1: 2093 | CB1: 2094 | CC1: 2095 | CD1: 2096 | CE1: 2097 | CF1: 2098 | CG1: 2099 | CH1: 2100
A2: bas | B2: a-GasBL | C2: 0.69378913 | D2: 0.69378913 | E2: 0.69378913 | F2: 0.69378913 | G2: 0.69378913 | H2: 0.69378913 | I2: 0.69378913 | J2: 0.69378913 | K2: 0.69378913 | L2: 0.69378913 | M2: 0.69378913 | N2: 0.69378913 | O2: 0.69378913 | P2: 0.69378913 | Q2: 0.69378913 | R2: 0.69378913 | S2: 0.69378913 | T2: 0.69378913 | U2: 0.69378913 | V2: 0.69378913 | W2: 0.69378913 | X2: 0.69378913 | Y2: 0.69378913 | Z2: 0.69378913 | AA2: 0.69378913 | AB2: 0.69378913 | AC2: 0.69378913 | AD2: 0.69378913 | AE2: 0.69378913 | AF2: 0.69378913 | AG2: 0.69378913 | AH2: 0.69378913 | AI2: 0.69378913 | AJ2: 0.69378913 | AK2: 0.69378913 | AL2: 0.69378913 | AM2: 0.69378913 | AN2: 0.69378913 | AO2: 0.69378913 | AP2: 0.69378913 | AQ2: 0.69378913 | AR2: 0.69378913 | AS2: 0.69378913 | AT2: 0.69378913 | AU2: 0.69378913 | AV2: 0.69378913 | AW2: 0.69378913 | AX2: 0.69378913 | AY2: 0.69378913 | AZ2: 0.69378913 | BA2: 0.69378913 | BB2: 0.69378913 | BC2: 0.69378913 | BD2: 0.69378913 | BE2: 0.69378913 | BF2: 0.69378913 | BG2: 0.69378913 | BH2: 0.69378913 | BI2: 0.69378913 | BJ2: 0.69378913 | BK2: 0.69378913 | BL2: 0.69378913 | BM2: 0.69378913 | BN2: 0.69378913 | BO2: 0.69378913 | BP2: 0.69378913 | BQ2: 0.69378913 | BR2: 0.69378913 | BS2: 0.69378913 | BT2: 0.69378913 | BU2: 0.69378913 | BV2: 0.69378913 | BW2: 0.69378913 | BX2: 0.69378913 | BY2: 0.69378913 | BZ2: 0.69378913 | CA2: 0.69378913 | CB2: 0.69378913 | CC2: 0.69378913 | CD2: 0.69378913 | CE2: 0.69378913 | CF2: 0.69378913 | CG2: 0.69378913 | CH2: 0.69378913
A3: bas | B3: a-GasP | C3: 0.27361177 | D3: 0.27361177 | E3: 0.27361177 | F3: 0.27361177 | G3: 0.27361177 | H3: 0.27361177 | I3: 0.27361177 | J3: 0.27361177 | K3: 0.27361177 | L3: 0.27361177 | M3: 0.27361177 | N3: 0.27361177 | O3: 0.27361177 | P3: 0.27361177 | Q3: 0.27361177 | R3: 0.27361177 | S3: 0.27361177 | T3: 0.27361177 | U3: 0.27361177 | V3: 0.27361177 | W3: 0.27361177 | X3: 0.27361177 | Y3: 0.27361177 | Z3: 0.27361177 | AA3: 0.27361177 | AB3: 0.27361177 | AC3: 0.27361177 | AD3: 0.27361177 | AE3: 0.27361177 | AF3: 0.27361177 | AG3: 0.27361177 | AH3: 0.27361177 | AI3: 0.27361177 | AJ3: 0.27361177 | AK3: 0.27361177 | AL3: 0.27361177 | AM3: 0.27361177 | AN3: 0.27361177 | AO3: 0.27361177 | AP3: 0.27361177 | AQ3: 0.27361177 | AR3: 0.27361177 | AS3: 0.27361177 | AT3: 0.27361177 | AU3: 0.27361177 | AV3: 0.27361177 | AW3: 0.27361177 | AX3: 0.27361177 | AY3: 0.27361177 | AZ3: 0.27361177 | BA3: 0.27361177 | BB3: 0.27361177 | BC3: 0.27361177 | BD3: 0.27361177 | BE3: 0.27361177 | BF3: 0.27361177 | BG3: 0.27361177 | BH3: 0.27361177 | BI3: 0.27361177 | BJ3: 0.27361177 | BK3: 0.27361177 | BL3: 0.27361177 | BM3: 0.27361177 | BN3: 0.27361177 | BO3: 0.27361177 | BP3: 0.27361177 | BQ3: 0.27361177 | BR3: 0.27361177 | BS3: 0.27361177 | BT3: 0.27361177 | BU3: 0.27361177 | BV3: 0.27361177 | BW3: 0.27361177 | BX3: 0.27361177 | BY3: 0.27361177 | BZ3: 0.27361177 | CA3: 0.27361177 | CB3: 0.27361177 | CC3: 0.27361177 | CD3: 0.27361177 | CE3: 0.27361177 | CF3: 0.27361177 | CG3: 0.27361177 | CH3: 0.27361177
A4: bas | B4: a-OilP | C4: 0.029590738 | D4: 0.029590738 | E4: 0.029590738 | F4: 0.029590738 | G4: 0.029590738 | H4: 0.029590738 | I4: 0.029590738 | J4: 0.029590738 | K4: 0.029590738 | L4: 0.029590738 | M4: 0.029590738 | N4: 0.029590738 | O4: 0.029590738 | P4: 0.029590738 | Q4: 0.029590738 | R4: 0.029590738 | S4: 0.029590738 | T4: 0.029590738 | U4: 0.029590738 | V4: 0.029590738 | W4: 0.029590738 | X4: 0.029590738 | Y4: 0.029590738 | Z4: 0.029590738 | AA4: 0.029590738 | AB4: 0.029590738 | AC4: 0.029590738 | AD4: 0.029590738 | AE4: 0.029590738 | AF4: 0.029590738 | AG4: 0.029590738 | AH4: 0.029590738 | AI4: 0.029590738 | AJ4: 0.029590738 | AK4: 0.029590738 | AL4: 0.029590738 | AM4: 0.029590738 | AN4: 0.029590738 | AO4: 0.029590738 | AP4: 0.029590738 | AQ4: 0.029590738 | AR4: 0.029590738 | AS4: 0.029590738 | AT4: 0.029590738 | AU4: 0.029590738 | AV4: 0.029590738 | AW4: 0.029590738 | AX4: 0.029590738 | AY4: 0.029590738 | AZ4: 0.029590738 | BA4: 0.029590738 | BB4: 0.029590738 | BC4: 0.029590738 | BD4: 0.029590738 | BE4: 0.029590738 | BF4: 0.029590738 | BG4: 0.029590738 | BH4: 0.029590738 | BI4: 0.029590738 | BJ4: 0.029590738 | BK4: 0.029590738 | BL4: 0.029590738 | BM4: 0.029590738 | BN4: 0.029590738 | BO4: 0.029590738 | BP4: 0.029590738 | BQ4: 0.029590738 | BR4: 0.029590738 | BS4: 0.029590738 | BT4: 0.029590738 | BU4: 0.029590738 | BV4: 0.029590738 | BW4: 0.029590738 | BX4: 0.029590738 | BY4: 0.029590738 | BZ4: 0.029590738 | CA4: 0.029590738 | CB4: 0.029590738 | CC4: 0.029590738 | CD4: 0.029590738 | CE4: 0.029590738 | CF4: 0.029590738 | CG4: 0.029590738 | CH4: 0.029590738
A5: bas | B5: a-SolarP | C5: 0.0030083583 | D5: 0.0030083583 | E5: 0.0030083583 | F5: 0.0030083583 | G5: 0.0030083583 | H5: 0.0030083583 | I5: 0.0030083583 | J5: 0.0030083583 | K5: 0.0030083583 | L5: 0.0030083583 | M5: 0.0030083583 | N5: 0.0030083583 | O5: 0.0030083583 | P5: 0.0030083583 | Q5: 0.0030083583 | R5: 0.0030083583 | S5: 0.0030083583 | T5: 0.0030083583 | U5: 0.0030083583 | V5: 0.0030083583 | W5: 0.0030083583 | X5: 0.0030083583 | Y5: 0.0030083583 | Z5: 0.0030083583 | AA5: 0.0030083583 | AB5: 0.0030083583 | AC5: 0.0030083583 | AD5: 0.0030083583 | AE5: 0.0030083583 | AF5: 0.0030083583 | AG5: 0.0030083583 | AH5: 0.0030083583 | AI5: 0.0030083583 | AJ5: 0.0030083583 | AK5: 0.0030083583 | AL5: 0.0030083583 | AM5: 0.0030083583 | AN5: 0.0030083583 | AO5: 0.0030083583 | AP5: 0.0030083583 | AQ5: 0.0030083583 | AR5: 0.0030083583 | AS5: 0.0030083583 | AT5: 0.0030083583 | AU5: 0.0030083583 | AV5: 0.0030083583 | AW5: 0.0030083583 | AX5: 0.0030083583 | AY5: 0.0030083583 | AZ5: 0.0030083583 | BA5: 0.0030083583 | BB5: 0.0030083583 | BC5: 0.0030083583 | BD5: 0.0030083583 | BE5: 0.0030083583 | BF5: 0.0030083583 | BG5: 0.0030083583 | BH5: 0.0030083583 | BI5: 0.0030083583 | BJ5: 0.0030083583 | BK5: 0.0030083583 | BL5: 0.0030083583 | BM5: 0.0030083583 | BN5: 0.0030083583 | BO5: 0.0030083583 | BP5: 0.0030083583 | BQ5: 0.0030083583 | BR5: 0.0030083583 | BS5: 0.0030083583 | BT5: 0.0030083583 | BU5: 0.0030083583 | BV5: 0.0030083583 | BW5: 0.0030083583 | BX5: 0.0030083583 | BY5: 0.0030083583 | BZ5: 0.0030083583 | CA5: 0.0030083583 | CB5: 0.0030083583 | CC5: 0.0030083583 | CD5: 0.0030083583 | CE5: 0.0030083583 | CF5: 0.0030083583 | CG5: 0.0030083583 | CH5: 0.0030083583
A6: bas | B6: elecPrice | C6: 1 | D6: 1 | E6: 1 | F6: 1 | G6: 1 | H6: 1 | I6: 1 | J6: 1 | K6: 1 | L6: 1 | M6: 1 | N6: 1 | O6: 1 | P6: 1 | Q6: 1 | R6: 1 | S6: 1 | T6: 1 | U6: 1 | V6: 1 | W6: 1 | X6: 1 | Y6: 1 | Z6: 1 | AA6: 1 | AB6: 1 | AC6: 1 | AD6: 1 | AE6: 1 | AF6: 1 | AG6: 1 | AH6: 1 | AI6: 1 | AJ6: 1 | AK6: 1 | AL6: 1 | AM6: 1 | AN6: 1 | AO6: 1 | AP6: 1 | AQ6: 1 | AR6: 1 | AS6: 1 | AT6: 1 | AU6: 1 | AV6: 1 | AW6: 1 | AX6: 1 | AY6: 1 | AZ6: 1 | BA6: 1 | BB6: 1 | BC6: 1 | BD6: 1 | BE6: 1 | BF6: 1 | BG6: 1 | BH6: 1 | BI6: 1 | BJ6: 1 | BK6: 1 | BL6: 1 | BM6: 1 | BN6: 1 | BO6: 1 | BP6: 1 | BQ6: 1 | BR6: 1 | BS6: 1 | BT6: 1 | BU6: 1 | BV6: 1 | BW6: 1 | BX6: 1 | BY6: 1 | BZ6: 1 | CA6: 1 | CB6: 1 | CC6: 1 | CD6: 1 | CE6: 1 | CF6: 1 | CG6: 1 | CH6: 1

Sheet EmiInv
B1: co2 | C1: n2o | D1: ch4 | E1: f-gas
A2: ElecHeat | B2: na
A3: Build
A4: Trans
A5: ManuCons
A6: OthEner
A7: Fugi
A8: Indu
A9: Waste
A10: Agri
A11: LULUCF
A12: BunkerFuels

Sheet mapK
C2: Crops | D2: MeatDairy | E2: FoodOther | F2: Clothing | G2: Manu | H2: Hot_Trad | I2: care_hht | J2: Serv | K2: privTrs | L2: privTrsEner | M2: privTrsRest | N2: Trans | O2: enerGas | P2: enerFossil | Q2: enerEle | R2: HousEner
C3: 0.5 | D3: 0.25 | E3: 0.25 | F3: 0.25 | G3: 0.25 | H3: 0.2 | I3: 2 | J3: 0.25 | K3: 0.1 | L3: eps | M3: 0.1 | N3: 0.25 | O3: 0.1 | P3: 0.25 | Q3: 0.1 | R3: 0.25
C5: Crops | D5: MeatDairy | E5: FoodOther | F5: Clothing | G5: Manu | H5: Hot_Trad | I5: care_hht | J5: Serv | K5: privTrs | L5: privTrsEner | M5: privTrsRest | N5: Trans | O5: enerGas | P5: enerFossil | Q5: EnerEle | R5: HousEner
B6: c-pdr | C6: 1
B7: c-wht | C7: 1
B8: c-gro | C8: 1
B9: c-v_f | C9: 1
B10: c-osd | C10: 1
B11: c-c_b | C11: 1
B12: c-ocr | C12: 1
B13: c-ctl | D13: 1
B14: c-ctlRais | D14: 1
B15: c-oap | D15: 1
B16: c-rmk | D16: 1
B17: c-fsh | D17: 1
B18: c-cmt | D18: 1
B19: c-omt | D19: 1
B20: c-mil | D20: 1
B21: c-trd | D21: 0.05 | E21: 0.1 | F21: 0.1 | G21: 0.05 | H21: 0.6 | M21: 0.1
B22: c-vol | E22: 1
B23: c-pcr | E23: 1
B24: c-sgr | E24: 1
B25: c-ofd | E25: 1
B26: c-b_t | E26: 1
B27: c-pfb | F27: 1
B28: c-wol | F28: 1
B29: c-tex | F29: 1
B30: c-lea | F30: 1
B31: c-wap | F31: 1
B32: c-frs | G32: 0.5 | R32: 0.5
B33: c-oxt | G33: 1
B34: c-lum | G34: 1
B35: c-chm | G35: 1
B36: c-bph | G36: 1
B37: c-nmm | G37: 1
B38: c-i_s | G38: 1
B39: c-nfm | G39: 1
B40: c-fmp | G40: 1
B41: c-ele | G41: 1
B42: c-omf | G42: 1
B43: c-ppp | G43: 1
B44: c-eeq | G44: 1
... B48: c-cns | G48: 1
B49: c-whs | H49: 1
B50: c-afs | H50: 1
B51: c-care | I51: 1
B52: c-hht | I52: 1
B53: care_hht | J53: 1
B54: c-edu | J54: 1
B55: c-cmn | J55: 1
B56: c-ofi | J56: 1
B57: c-ins | J57: 0.8 | M57: 0.2
B58: c-osr | J58: 1
B59: c-osg | J59: 1
B60: c-ros | J60: 1
B61: c-obs | J61: 1
B62: c-dwe | J62: 1
B63: c-rsa | J63: 1
B64: c-macc | J64: 1
B65: privTrsEner | K65: 1
B66: privTrsRest | K66: 1
B67: c-p_c | L67: 0.5 | P67: 0.5
B68: c-otp | M68: 1
B69: c-mvh | M69: 1
B70: c-otn | M70: 1
B71: c-wtp | N71: 1
B72: c-atp | N72: 1
B73: privTrs | N73: 1
B74: c-gas | O74: 1
B75: c-gdt | O75: 1
B76: enerGas | P76: 1
B77: c-coa | P77: 1
B78: c-oil | P78: 1
B79: c-TnD | Q79: 1
B80: c-ely | Q80: 1
B81: enerFossil | R81: 1
B82: enerEle | R82: 1

Sheet pnest
D2: labsk | E2: labus | F2: labsk_labus | G2: cap_labSk | H2: va | I2: cap_labsk_ener | J2: ener | K2: ely_tnd | L2: gas_gdt | M2: ener_gasoil | N2: ener_fossil | O2: aez_land | P2: crops | Q2: anim_meat | R2: f-top | S2: nd | T2: wtr_land | U2: nd_wtr_land | V2: crops_land
C3: subsElas | D3: 0.5 | E3: 0.5 | F3: 0.25 | G3: 0.2 | H3: 0.7 | I3: 0.25 | J3: 0.5 | K3: eps | L3: eps | M3: 0.7 | N3: 0.5 | O3: 7.5 | P3: 2 | Q3: 2 | R3: eps | S3: eps | T3: 0.5 | U3: 0.25 | V3: 0.5
C4: additive | J4: 1 | M4: 1 | N4: 1
D6: labsk | E6: labus | F6: labsk_labus | G6: cap_labSk | H6: va | I6: cap_labsk_ener | J6: ener | K6: ely_tnd | L6: gas_gdt | M6: ener_gasoil | N6: ener_fossil | O6: aez_land | P6: crops | Q6: anim_meat | R6: f-top | S6: nd | T6: wtr_land | U6: nd_wtr_land | V6: crops_land
B7: all | C7: f-off_mgr_pros | D7: 1
B8: all | C8: f-tech_aspros | D8: 1
B9: all | C9: f-m_off_mgr_pros | D9: 1
B10: all | C10: f-m_tech_aspros | D10: 1
B11: all | C11: f-f_off_mgr_pros | D11: 1
B12: all | C12: f-f_tech_aspros | D12: 1
B13: all | C13: f-m_skl | D13: 1
B14: all | C14: f-f_skl | D14: 1
B15: all | C15: f-clerks | E15: 1
B16: all | C16: f-service_shop | E16: 1
B17: all | C17: f-ag_othlowsk | E17: 1
B18: all | C18: f-m_clerks | E18: 1
B19: all | C19: f-m_service_shop | E19: 1
B20: all | C20: f-m_ag_othlowsk | E20: 1
B21: all | C21: f-f_clerks | E21: 1
B22: all | C22: f-f_service_shop | E22: 1
B23: all | C23: f-f_ag_othlowsk | E23: 1
B24: all | C24: f-m_nsk | E24: 1
B25: all | C25: f-f_nsk | E25: 1
B26: all | C26: labus | F26: 1
B27: all | C27: labsk | F27: 0.5 | G27: 0.5
B28: all | C28: f-Capital | G28: 1
B29: all | C29: f-NatlRes | H29: 1
B30: all | C30: labsk_labus | H30: 1
B31: all | C31: cap_labsk_ener | H31: 1
B32: all | C32: f-land | H32: 1
B33: all | C33: f-water | H33: 1 | T33: eps | U33: eps | V33: eps
B34: all | C34: aez_land | H34: 1
B35: a-pdr | C35: nd_wtr_land | H35: 1
B36: a-wht | C36: nd_wtr_land | H36: 1
B37: a-gro | C37: nd_wtr_land | H37: 1
B38: a-v_f | C38: nd_wtr_land | H38: 1
B39: a-osd | C39: nd_wtr_land | H39: 1
B40: a-c_b | C40: nd_wtr_land | H40: 1
B41: a-pfb | C41: nd_wtr_land | H41: 1
B42: a-ocr | C42: nd_wtr_land | H42: 1
B43: a-ctl | C43: crops_land | H43: 1
B44: a-oap | C44: crops_land | H44: 1
B45: a-rmk | C45: crops_land | H45: 1
... B47: a-wol | C47: crops_land | H47: 1
B48: all | C48: cap_labSk | I48: 1
B49: all | C49: ener | I49: 1
B50: all | C50: ener_fossil | J50: 1
B51: all | C51: ely_tnd | J51: 1
B52: all | C52: c-p_c | J52: 1
B53: all | C53: c-TnD | K53: 1
B54: all | C54: c-ely | K54: 1
B55: all | C55: c-gdt | L55: 1
B56: all | C56: c-gas | L56: 1
B57: all | C57: c-oil | M57: 1
B58: all | C58: gas_gdt | M58: 1
B59: all | C59: ener_gasoil | N59: 1
B60: all | C60: c-coa | N60: 1
B61: all | C61: f-AEZ1 | O61: 1
B62: all | C62: f-AEZ2 | O62: 1
B63: all | C63: f-AEZ3 | O63: 1
B64: all | C64: f-AEZ4 | O64: 1
B65: all | C65: f-AEZ5 | O65: 1
B66: all | C66: f-AEZ6 | O66: 1
B67: all | C67: f-AEZ7 | O67: 1
B68: all | C68: f-AEZ8 | O68: 1
B69: all | C69: f-AEZ9 | O69: 1
B70: all | C70: f-AEZ10 | O70: 1
B71: all | C71: f-AEZ11 | O71: 1
B72: all | C72: f-AEZ12 | O72: 1
... B78: all | C78: f-AEZ18 | O78: 1
B79: all | C79: c-pdr | P79: 1
B80: all | C80: c-wht | P80: 1
B81: all | C81: c-gro | P81: 1
B82: all | C82: c-v_f | P82: 1
B83: all | C83: c-osd | P83: 1
B84: all | C84: c-c_b | P84: 1
B85: all | C85: c-pfb | P85: 1
B86: all | C86: c-ocr | P86: 1
B87: all | C87: c-pcr | P87: 1
B88: all | C88: c-ctl | Q88: 1
B89: all | C89: c-ctlRais | Q89: 1
B90: all | C90: c-oap | Q90: 1
B91: all | C91: c-rmk | Q91: 1
B92: all | C92: c-wol | Q92: 1
B93: all | C93: c-cmt | Q93: 1
B94: all | C94: c-omt | Q94: 1
B95: all | C95: va | R95: 1
B96: all | C96: nd | R96: 1
B97: a-pdr | C97: nd | R97: 0.5 | U97: 0.5
B98: a-wht | C98: nd | R98: 0.5 | U98: 0.5
B99: a-gro | C99: nd | R99: 0.5 | U99: 0.5
B100: a-v_f | C100: nd | R100: 0.5 | U100: 0.5
B101: a-osd | C101: nd | R101: 0.5 | U101: 0.5
B102: a-c_b | C102: nd | R102: 0.5 | U102: 0.5
B103: a-pfb | C103: nd | R103: 0.5 | U103: 0.5
B104: a-ocr | C104: nd | R104: 0.5 | U104: 0.5
B105: all | C105: crops | S105: 1
B106: all | C106: anim_meat | S106: 1
B107: all | C107: c-frs | S107: 1
B108: all | C108: c-fsh | S108: 1
...

Sheet defPar
A1: Explanation | B1: parameter | C1: value
A2: Elasticity between demand bundles other final Demand | B2: sigmaf0 | C2: 1.01
A3: Elasticity between savings and total consumption | B3: omegaSav0 | C3: 0.2
A4: Elasticity between savings and transfers to HHs | B4: omegaSavEntr0 | C4: 0.05
A5: Elasticity between government and private bonds | B5: omegaFund0 | C5: 4
A6: Elasticity of capital supply to capital stock | B6: epsRor0 | C6: Eps
A7: Elasticity of expected return on capital to capital stock | B7: epsRorE0 | C7: 0.9
A8: Share of investment that is not added to capital stock | B8: PhiPcInv0 | C8: 0.75
A9: Depreciation rate | B9: depr0 | C9: 0.04
A10: Capital stock GDP ratio | B10: capoutRate0 | C10: 2.6164447
A11: Elasticity of labor productivity to air pollution | B11: AirpolEff0 | C11: 0.025
A12: Elasticity among commodities when an activity produces multiple commodities | B12: omegap0 | C12: 0.2
A13: Disinvestment Elasticity for declining sectors | B13: invElas0 | C13: 0.7
A14: Elasticity among activities when a commodity is produced by multiple activities | B14: sigmas0 | C14: +Inf
A15: Elasticity between imports and domestic demand | B15: sigmam0 | C15: 5
A16: Elasticity between exports and domestic supply | B16: omegax0 | C16: 3
A17: Elasticity between margin commodities | B17: sigmamg0 | C17: 0.01
A18: Import supply Elasticity | B18: omegam0 | C18: +Inf
A19: Export demand Elasticity | B19: etae0 | C19: +Inf
A20: debt to gdp default threshhold, used in specific savf closure | B20: omegasavf0 | C20: 0.5
A21: positive scaling parameter, used in specific savf closure | B21: rhosavf0 | C21: 10
A22: Country risk premium | B22: riskPrem0 | C22: 1
A23: expected return rate in the row | B23: retrow0 | C23: 0.05
A24: expected per capita GDP growth rate in the row | B24: ggdppcrow0 | C24: 0.02
A25: efficiency param. returns | B25: eta10 | C25: 7
A26: efficiency param. GDP p.c. growth | B26: eta20 | C26: 7
A27: efficiency param. returns | B27: eta1a0 | C27: 7
A28: efficiency param. GDP p.c. growth | B28: eta2a0 | C28: 7
A29: Elasticity of foreign new public debt to interest rate | B29: sigmaFInt0 | C29: 1
A30: Threshold after which gov consumption is dampended | B30: debtGdpTgt0 | C30: 0.10143832
A31: Default income elasticity for aggregate commodity group (overwritten by hohpar) | B31: incElas0 | C31: 0.735
... A42: Elasticity of stock changes to targeted stock over production | B42: rhoXDelSt0 | C42: 0.25
A43: Target stock over production level | B43: alphaSt0 | C43: Eps
B44: GDP | C44: 169776.37

Sheet fmNest
C1: Only used if AEZ not found | D1: Only used if AEZ not found | E1: Only used if AEZ not found | F1: Only used if AEZ not found | H1: Immobile; Numbers for activities are activity specific factor supply elasticities | J1: All activities not in agrLab and manulab, automatically assigned to not listed activities | K1: All activities, automatically assigned to all actibitiy as no entry | L1: All activities, automatically assigned to all actibitiy as no entry | M1: All labor categories have the segments defined agrLab, manuLab, restLab | R1: All labor categories have the segments defined agrLab, manuLab, restLab | W1: All labor categories have the segments defined agrLab, manuLab, restLab | AB1: Gender differentiated labor and the 5 skill levels are never active simultaneously | AW1: cropLand by AEZ | BO1: grassland by AEZ | CG1: agrland by AEZ | CY1: Total land by AEZ, aggregated to aez_land (total land) in production function
C2: cropLand | D2: grasLand | E2: agrLand | F2: f-land | G2: agrLab | H2: f-natlRes | I2: manuLab | J2: restLab | K2: f-capital | L2: f-water | M2: f-tech_aspros | N2: f-service_shop | O2: f-off_mgr_pros | P2: f-ag_othlowsk | Q2: f-clerks | R2: f-m_tech_aspros | S2: f-m_service_shop | T2: f-m_off_mgr_pros | U2: f-m_ag_othlowsk | V2: f-m_clerks | W2: f-f_tech_aspros | X2: f-f_service_shop | Y2: f-f_off_mgr_pros | Z2: f-f_ag_othlowsk | AA2: f-f_clerks | AB2: f-m_skl | AC2: f-f_skl | AD2: f-m_nsk | AE2: f-f_nsk | AF2: f-f_tech_aspros_rest | AG2: f-f_service_shop_rest | AH2: f-f_off_mgr_pros_rest | AI2: f-f_ag_othlowsk_rest | AJ2: f-f_clerks_rest | AK2: f-f_skl_rest | AL2: f-f_nsk_rest | AM2: f-f_tech_aspros_care | AN2: f-f_service_shop_care | AO2: f-f_off_mgr_pros_care | AP2: f-f_ag_othlowsk_care | AQ2: f-f_clerks_care | AR2: f-f_skl_care | AS2: f-f_nsk_care | AT2: AEZ1_cropLand | AU2: AEZ2_cropLand | AV2: AEZ3_cropLand | AW2: AEZ4_cropLand | AX2: AEZ5_cropLand | AY2: AEZ6_cropLand | AZ2: AEZ7_cropLand | BA2: AEZ8_cropLand | BB2: AEZ9_cropLand | BC2: AEZ10_cropLand | BD2: AEZ11_cropLand | BE2: AEZ12_cropLand | BF2: AEZ13_cropLand | BG2: AEZ14_cropLand | BH2: AEZ15_cropLand | BI2: AEZ16_cropLand | BJ2: AEZ17_cropLand | BK2: AEZ18_cropLand | BL2: AEZ1_grasLand | BM2: AEZ2_grasLand | BN2: AEZ3_grasLand | BO2: AEZ4_grasLand | BP2: AEZ5_grasLand | BQ2: AEZ6_grasLand | BR2: AEZ7_grasLand | BS2: AEZ8_grasLand | BT2: AEZ9_grasLand | BU2: AEZ10_grasLand | BV2: AEZ11_grasLand | BW2: AEZ12_grasLand | BX2: AEZ13_grasLand | BY2: AEZ14_grasLand | BZ2: AEZ15_grasLand | CA2: AEZ16_grasLand | CB2: AEZ17_grasLand | CC2: AEZ18_grasLand | CD2: AEZ1_agrLand | CE2: AEZ2_agrLand | CF2: AEZ3_agrLand | CG2: AEZ4_agrLand | CH2: AEZ5_agrLand | CI2: AEZ6_agrLand | CJ2: AEZ7_agrLand | CK2: AEZ8_agrLand | CL2: AEZ9_agrLand | CM2: AEZ10_agrLand | CN2: AEZ11_agrLand | CO2: AEZ12_agrLand | CP2: AEZ13_agrLand | CQ2: AEZ14_agrLand | CR2: AEZ15_agrLand | CS2: AEZ16_agrLand | CT2: AEZ17_agrLand | CU2: AEZ18_agrLand | CV2: f-AEZ1 | CW2: f-AEZ2 | CX2: f-AEZ3 | CY2: f-AEZ4 | CZ2: f-AEZ5 | DA2: f-AEZ6 | DB2: f-AEZ7 | DC2: f-AEZ8 | DD2: f-AEZ9 | DE2: f-AEZ10 | DF2: f-AEZ11 | DG2: f-AEZ12 | DH2: f-AEZ13 | DI2: f-AEZ14 | DJ2: f-AEZ15 | DK2: f-AEZ16 | DL2: f-AEZ17 | DM2: f-AEZ18
B3: additive | C3: 1 | D3: 1 | E3: 1 | F3: 1 | AT3: 1 | AU3: 1 | AV3: 1 | AW3: 1 | AX3: 1 | AY3: 1 | AZ3: 1 | BA3: 1 | BB3: 1 | BC3: 1 | BD3: 1 | BE3: 1 | BF3: 1 | BG3: 1 | BH3: 1 | BI3: 1 | BJ3: 1 | BK3: 1 | BL3: 1 | BM3: 1 | BN3: 1 | BO3: 1 | BP3: 1 | BQ3: 1 | BR3: 1 | BS3: 1 | BT3: 1 | BU3: 1 | BV3: 1 | BW3: 1 | BX3: 1 | BY3: 1 | BZ3: 1 | CA3: 1 | CB3: 1 | CC3: 1 | CD3: 1 | CE3: 1 | CF3: 1 | CG3: 1 | CH3: 1 | CI3: 1 | CJ3: 1 | CK3: 1 | CL3: 1 | CM3: 1 | CN3: 1 | CO3: 1 | CP3: 1 | CQ3: 1 | CR3: 1 | CS3: 1 | CT3: 1 | CU3: 1 | CV3: 1 | CW3: 1 | CX3: 1 | CY3: 1 | CZ3: 1 | DA3: 1 | DB3: 1 | DC3: 1 | DD3: 1 | DE3: 1 | DF3: 1 | DG3: 1 | DH3: 1 | DI3: 1 | DJ3: 1 | DK3: 1 | DL3: 1 | DM3: 1
B4: omegaCET | C4: 0.75 | D4: 0.75 | E4: 0.5 | F4: 0.25 | G4: inf | H4: eps | I4: inf | J4: inf | K4: inf | L4: 0.75 | M4: 2 | N4: 2 | O4: 2 | P4: 2 | Q4: 2 | R4: 2 | S4: 2 | T4: 2 | U4: 2 | V4: 2 | W4: 0.5 | X4: 0.5 | Y4: 0.5 | Z4: 0.5 | AA4: 0.5 | AB4: 2 | AC4: 0.5 | AD4: 2 | AE4: 0.5 | AF4: 2 | AG4: 2 | AH4: 2 | AI4: 2 | AJ4: 2 | AK4: 2 | AL4: 2 | AM4: eps | AN4: eps | AO4: eps | AP4: eps | AQ4: eps | AR4: eps | AS4: eps | AT4: 0.75 | AU4: 0.75 | AV4: 0.75 | AW4: 0.75 | AX4: 0.75 | AY4: 0.75 | AZ4: 0.75 | BA4: 0.75 | BB4: 0.75 | BC4: 0.75 | BD4: 0.75 | BE4: 0.75 | BF4: 0.75 | BG4: 0.75 | BH4: 0.75 | BI4: 0.75 | BJ4: 0.75 | BK4: 0.75 | BL4: 0.75 | BM4: 0.75 | BN4: 0.75 | BO4: 0.75 | BP4: 0.75 | BQ4: 0.75 | BR4: 0.75 | BS4: 0.75 | BT4: 0.75 | BU4: 0.75 | BV4: 0.75 | BW4: 0.75 | BX4: 0.75 | BY4: 0.75 | BZ4: 0.75 | CA4: 0.75 | CB4: 0.75 | CC4: 0.75 | CD4: 0.5 | CE4: 0.5 | CF4: 0.5 | CG4: 0.5 | CH4: 0.5 | CI4: 0.5 | CJ4: 0.5 | CK4: 0.5 | CL4: 0.5 | CM4: 0.5 | CN4: 0.5 | CO4: 0.5 | CP4: 0.5 | CQ4: 0.5 | CR4: 0.5 | CS4: 0.5 | CT4: 0.5 | CU4: 0.5 | CV4: 0.25 | CW4: 0.25 | CX4: 0.25 | CY4: 0.25 | CZ4: 0.25 | DA4: 0.25 | DB4: 0.25 | DC4: 0.25 | DD4: 0.25 | DE4: 0.25 | DF4: 0.25 | DG4: 0.25 | DH4: 0.25 | DI4: 0.25 | DJ4: 0.25 | DK4: 0.25 | DL4: 0.25 | DM4: 0.25
B5: omegaCETShort | C5: eps | D5: eps | E5: eps | F5: eps | G5: eps | H5: eps | I5: 1.01 | J5: 1.01 | K5: eps | L5: 0.25 | M5: 1.01 | N5: 1.01 | O5: 1.01 | P5: 1.01 | Q5: 1.01 | R5: 1.01 | S5: 1.01 | T5: 1.01 | U5: 1.01 | V5: 1.01 | W5: 0.05 | X5: 0.05 | Y5: 0.05 | Z5: 0.05 | AA5: 0.05 | AB5: 1.01 | AC5: 0.05 | AD5: 1.01 | AE5: 0.05 | AF5: 1.01 | AG5: 1.01 | AH5: 1.01 | AI5: 1.01 | AJ5: 1.01 | AK5: 1.01 | AL5: 1.01 | AM5: eps | AN5: eps | AO5: eps | AP5: eps | AQ5: eps | AR5: eps | AS5: eps | AT5: 0.75 | AU5: 0.75 | AV5: 0.75 | AW5: 0.75 | AX5: 0.75 | AY5: 0.75 | AZ5: 0.75 | BA5: 0.75 | BB5: 0.75 | BC5: 0.75 | BD5: 0.75 | BE5: 0.75 | BF5: 0.75 | BG5: 0.75 | BH5: 0.75 | BI5: 0.75 | BJ5: eps | BK5: eps | BL5: 0.75 | BM5: 0.75 | BN5: 0.75 | BO5: 0.75 | BP5: 0.75 | BQ5: 0.75 | BR5: 0.75 | BS5: 0.75 | BT5: 0.75 | BU5: 0.75 | BV5: 0.75 | BW5: 0.75 | BX5: 0.75 | BY5: 0.75 | BZ5: 0.75 | CA5: 0.75 | CB5: 0.75 | CC5: 0.75 | CD5: 0.5 | CE5: 0.5 | CF5: 0.5 | CG5: 0.5 | CH5: 0.5 | CI5: 0.5 | CJ5: 0.5 | CK5: 0.5 | CL5: 0.5 | CM5: 0.5 | CN5: 0.5 | CO5: 0.5 | CP5: 0.5 | CQ5: 0.5 | CR5: 0.5 | CS5: 0.5 | CT5: 0.5 | CU5: 0.5 | CV5: eps | CW5: eps | CX5: eps | CY5: eps | CZ5: eps | DA5: eps | DB5: eps | DC5: eps | DD5: eps | DE5: eps | DF5: eps | DG5: eps | DH5: eps | DI5: eps | DJ5: eps | DK5: eps | DL5: eps | DM5: eps
B6: factSupElas | F6: 0.1 | M6: 0.2 | N6: 0.2 | O6: 0.2 | P6: 0.2 | Q6: 0.2 | R6: 0.2 | S6: 0.2 | T6: 0.2 | U6: 0.2 | V6: 0.2 | W6: 0.2 | X6: 0.2 | Y6: 0.2 | Z6: 0.2 | AA6: 0.2 | AB6: 0.2 | AC6: 0.2 | AD6: 0.2 | AE6: 0.2 | CV6: 0.1 | CW6: 0.1 | CX6: 0.1 | CY6: 0.1 | CZ6: 0.1 | DA6: 0.1 | DB6: 0.1 | DC6: 0.1 | DD6: 0.1 | DE6: 0.1 | DF6: 0.1 | DG6: 0.1 | DH6: 0.1 | DI6: 0.1 | DJ6: 0.1 | DK6: 0.1 | DL6: 0.1 | DM6: 0.1
B7: factSupElasShort | F7: eps | L7: 0.01 | M7: eps | N7: eps | O7: eps | P7: eps | Q7: eps | R7: eps | S7: eps | T7: eps | U7: eps | V7: eps | W7: eps | X7: eps | Y7: eps | Z7: eps | AA7: eps | AB7: eps | AC7: eps | AD7: eps | AE7: eps | CV7: eps | CW7: eps | CX7: eps | CY7: eps | CZ7: eps | DA7: eps | DB7: eps | DC7: eps | DD7: eps | DE7: eps | DF7: eps | DG7: eps | DH7: eps | DI7: eps | DJ7: eps | DK7: eps | DL7: eps | DM7: eps
C9: cropLand | D9: grasLand | E9: agrLand | F9: f-land | G9: agrLab | H9: f-natlRes | I9: manuLab | J9: restLab | K9: f-capital | L9: f-water | M9: f-tech_aspros | N9: f-service_shop | O9: f-off_mgr_pros | P9: f-ag_othlowsk | Q9: f-clerks | R9: f-m_tech_aspros | S9: f-m_service_shop | T9: f-m_off_mgr_pros | U9: f-m_ag_othlowsk | V9: f-m_clerks | W9: f-f_tech_aspros | X9: f-f_service_shop | Y9: f-f_off_mgr_pros | Z9: f-f_ag_othlowsk | AA9: f-f_clerks | AB9: f-m_skl | AC9: f-f_skl | AD9: f-m_nsk | AE9: f-f_nsk | AF9: f-f_tech_aspros_rest | AG9: f-f_service_shop_rest | AH9: f-f_off_mgr_pros_rest | AI9: f-f_ag_othlowsk_rest | AJ9: f-f_clerks_rest | AK9: f-f_skl_rest | AL9: f-f_nsk_rest | AM9: f-f_tech_aspros_care | AN9: f-f_service_shop_care | AO9: f-f_off_mgr_pros_care | AP9: f-f_ag_othlowsk_care | AQ9: f-f_clerks_care | AR9: f-f_skl_care | AS9: f-f_nsk_care | AT9: AEZ1_cropLand | AU9: AEZ2_cropLand | AV9: AEZ3_cropLand | AW9: AEZ4_cropLand | AX9: AEZ5_cropLand | AY9: AEZ6_cropLand | AZ9: AEZ7_cropLand | BA9: AEZ8_cropLand | BB9: AEZ9_cropLand | BC9: AEZ10_cropLand | BD9: AEZ11_cropLand | BE9: AEZ12_cropLand | BF9: AEZ13_cropLand | BG9: AEZ14_cropLand | BH9: AEZ15_cropLand | BI9: AEZ16_cropLand | BJ9: AEZ17_cropLand | BK9: AEZ18_cropLand | BL9: AEZ1_grasLand | BM9: AEZ2_grasLand | BN9: AEZ3_grasLand | BO9: AEZ4_grasLand | BP9: AEZ5_grasLand | BQ9: AEZ6_grasLand | BR9: AEZ7_grasLand | BS9: AEZ8_grasLand | BT9: AEZ9_grasLand | BU9: AEZ10_grasLand | BV9: AEZ11_grasLand | BW9: AEZ12_grasLand | BX9: AEZ13_grasLand | BY9: AEZ14_grasLand | BZ9: AEZ15_grasLand | CA9: AEZ16_grasLand | CB9: AEZ17_grasLand | CC9: AEZ18_grasLand | CD9: AEZ1_agrLand | CE9: AEZ2_agrLand | CF9: AEZ3_agrLand | CG9: AEZ4_agrLand | CH9: AEZ5_agrLand | CI9: AEZ6_agrLand | CJ9: AEZ7_agrLand | CK9: AEZ8_agrLand | CL9: AEZ9_agrLand | CM9: AEZ10_agrLand | CN9: AEZ11_agrLand | CO9: AEZ12_agrLand | CP9: AEZ13_agrLand | CQ9: AEZ14_agrLand | CR9: AEZ15_agrLand | CS9: AEZ16_agrLand | CT9: AEZ17_agrLand | CU9: AEZ18_agrLand | CV9: f-AEZ1 | CW9: f-AEZ2 | CX9: f-AEZ3 | CY9: f-AEZ4 | CZ9: f-AEZ5 | DA9: f-AEZ6 | DB9: f-AEZ7 | DC9: f-AEZ8 | DD9: f-AEZ9 | DE9: f-AEZ10 | DF9: f-AEZ11 | DG9: f-AEZ12 | DH9: f-AEZ13 | DI9: f-AEZ14 | DJ9: f-AEZ15 | DK9: f-AEZ16 | DL9: f-AEZ17 | DM9: f-AEZ18
B10: a-care | AM10: 1 | AN10: 1 | AO10: 1 | AP10: 1 | AQ10: 1 | AR10: 1 | AS10: 1
B11: a-pdr | C11: 1 | G11: 1 | AT11: 1 | AU11: 1 | AV11: 1 | AW11: 1 | AX11: 1 | AY11: 1 | AZ11: 1 | BA11: 1 | BB11: 1 | BC11: 1 | BD11: 1 | BE11: 1 | BF11: 1 | BG11: 1 | BH11: 1 | BI11: 1 | BJ11: 1 | BK11: 1
B12: a-wht | C12: 1 | G12: 1 | AT12: 1 | AU12: 1 | AV12: 1 | AW12: 1 | AX12: 1 | AY12: 1 | AZ12: 1 | BA12: 1 | BB12: 1 | BC12: 1 | BD12: 1 | BE12: 1 | BF12: 1 | BG12: 1 | BH12: 1 | BI12: 1 | BJ12: 1 | BK12: 1
B13: a-gro | C13: 1 | G13: 1 | AT13: 1 | AU13: 1 | AV13: 1 | AW13: 1 | AX13: 1 | AY13: 1 | AZ13: 1 | BA13: 1 | BB13: 1 | BC13: 1 | BD13: 1 | BE13: 1 | BF13: 1 | BG13: 1 | BH13: 1 | BI13: 1 | BJ13: 1 | BK13: 1
B14: a-v_f | C14: 1 | G14: 1 | AT14: 1 | AU14: 1 | AV14: 1 | AW14: 1 | AX14: 1 | AY14: 1 | AZ14: 1 | BA14: 1 | BB14: 1 | BC14: 1 | BD14: 1 | BE14: 1 | BF14: 1 | BG14: 1 | BH14: 1 | BI14: 1 | BJ14: 1 | BK14: 1
B15: a-osd | C15: 1 | G15: 1 | AT15: 1 | AU15: 1 | AV15: 1 | AW15: 1 | AX15: 1 | AY15: 1 | AZ15: 1 | BA15: 1 | BB15: 1 | BC15: 1 | BD15: 1 | BE15: 1 | BF15: 1 | BG15: 1 | BH15: 1 | BI15: 1 | BJ15: 1 | BK15: 1
B16: a-c_b | C16: 1 | G16: 1 | AT16: 1 | AU16: 1 | AV16: 1 | AW16: 1 | AX16: 1 | AY16: 1 | AZ16: 1 | BA16: 1 | BB16: 1 | BC16: 1 | BD16: 1 | BE16: 1 | BF16: 1 | BG16: 1 | BH16: 1 | BI16: 1 | BJ16: 1 | BK16: 1
B17: a-pfb | C17: 1 | G17: 1 | AT17: 1 | AU17: 1 | AV17: 1 | AW17: 1 | AX17: 1 | AY17: 1 | AZ17: 1 | BA17: 1 | BB17: 1 | BC17: 1 | BD17: 1 | BE17: 1 | BF17: 1 | BG17: 1 | BH17: 1 | BI17: 1 | BJ17: 1 | BK17: 1
B18: a-ocr | C18: 1 | G18: 1 | AT18: 1 | AU18: 1 | AV18: 1 | AW18: 1 | AX18: 1 | AY18: 1 | AZ18: 1 | BA18: 1 | BB18: 1 | BC18: 1 | BD18: 1 | BE18: 1 | BF18: 1 | BG18: 1 | BH18: 1 | BI18: 1 | BJ18: 1 | BK18: 1
B19: a-ctl | D19: 1 | G19: 1 | BL19: 1 | BM19: 1 | BN19: 1 | BO19: 1 | BP19: 1 | BQ19: 1 | BR19: 1 | BS19: 1 | BT19: 1 | BU19: 1 | BV19: 1 | BW19: 1 | BX19: 1 | BY19: 1 | BZ19: 1 | CA19: 1 | CB19: 1 | CC19: 1
B20: a-oap | D20: 1 | G20: 1 | BL20: 1 | BM20: 1 | BN20: 1 | BO20: 1 | BP20: 1 | BQ20: 1 | BR20: 1 | BS20: 1 | BT20: 1 | BU20: 1 | BV20: 1 | BW20: 1 | BX20: 1 | BY20: 1 | BZ20: 1 | CA20: 1 | CB20: 1 | CC20: 1
B21: a-rmk | D21: 1 | G21: 1 | BL21: 1 | BM21: 1 | BN21: 1 | BO21: 1 | BP21: 1 | BQ21: 1 | BR21: 1 | BS21: 1 | BT21: 1 | BU21: 1 | BV21: 1 | BW21: 1 | BX21: 1 | BY21: 1 | BZ21: 1 | CA21: 1 | CB21: 1 | CC21: 1
B22: a-ctlRais | D22: 1 | G22: 1 | BL22: 1 | BM22: 1 | BN22: 1 | BO22: 1 | BP22: 1 | BQ22: 1 | BR22: 1 | BS22: 1 | BT22: 1 | BU22: 1 | BV22: 1 | BW22: 1 | BX22: 1 | BY22: 1 | BZ22: 1 | CA22: 1 | CB22: 1 | CC22: 1
B23: a-wol | D23: 1 | G23: 1 | BL23: 1 | BM23: 1 | BN23: 1 | BO23: 1 | BP23: 1 | BQ23: 1 | BR23: 1 | BS23: 1 | BT23: 1 | BU23: 1 | BV23: 1 | BW23: 1 | BX23: 1 | BY23: 1 | BZ23: 1 | CA23: 1 | CB23: 1 | CC23: 1
B24: cropLand | E24: 1
B25: grasLand | E25: 1
B26: a-frs | F26: 1 | H26: 0.25 | I26: 1 | CV26: 1 | CW26: 1 | CX26: 1 | CY26: 1 | CZ26: 1 | DA26: 1 | DB26: 1 | DC26: 1 | DD26: 1 | DE26: 1 | DF26: 1 | DG26: 1 | DH26: 1 | DI26: 1 | DJ26: 1 | DK26: 1 | DL26: 1 | DM26: 1
B27: agrLand | F27: 1
B28: a-fsh | H28: 0.25 | I28: 1
B29: a-coa | H29: 0.25 | I29: 1
B30: a-oil | H30: 0.25 | I30: 1
B31: a-gas | H31: 0.25 | I31: 1
B32: a-oxt | H32: 0.25 | I32: 1
B33: a-cmt | I33: 1
B34: a-omt | I34: 1
B35: a-vol | I35: 1
B36: a-mil | I36: 1
B37: a-pcr | I37: 1
B38: a-sgr | I38: 1
B39: a-ofd | I39: 1
B40: a-b_t | I40: 1
B41: a-tex | I41: 1
B42: a-wap | I42: 1
B43: a-lea | I43: 1
B44: a-lum | I44: 1
... B73: a-wtr | I73: 1
B74: a-cns | J74: 1
B75: a-trd | J75: 1
B76: a-afs | J76: 1
B77: a-otp | J77: 1
B78: a-otpEle | J78: 1
B79: a-wtp | J79: 1
B80: a-atp | J80: 1
B81: a-whs | J81: 1
B82: a-cmn | J82: 1
B83: a-ofi | J83: 1
B84: a-ins | J84: 1
B85: a-rsa | J85: 1
... B92: a-macc | J92: 1
B93: f-f_tech_aspros_care | W93: 1
B94: f-f_service_shop_care | X94: 1
B95: f-f_off_mgr_pros_care | Y95: 1
B96: f-f_ag_othlowsk_care | Z96: 1
B97: f-f_clerks_care | AA97: 1
B98: f-f_skl_care | AC98: 1
B99: f-f_nsk_care | AE99: 1
B100: f-f_tech_aspros_rest | W100: 1
B101: f-f_service_shop_rest | X101: 1
B102: f-f_off_mgr_pros_rest | Y102: 1
B103: f-f_ag_othlowsk_rest | Z103: 1
B104: f-f_clerks_rest | AA104: 1
B105: f-f_skl_rest | AC105: 1
B106: f-f_nsk_rest | AE106: 1
B107: RestLab | M107: 1 | N107: 1 | O107: 1 | P107: 1 | Q107: 1 | R107: 1 | S107: 1 | T107: 1 | U107: 1 | V107: 1 | AB107: 1 | AD107: 1 | AF107: 1 | AG107: 1 | AH107: 1 | AI107: 1 | AJ107: 1 | AK107: 1 | AL107: 1
B108: agrLab | M108: 1 | N108: 1 | O108: 1 | P108: 1 | Q108: 1 | R108: 1 | S108: 1 | T108: 1 | U108: 1 | V108: 1 | AB108: 1 | AD108: 1 | AF108: 1 | AG108: 1 | AH108: 1 | AI108: 1 | AJ108: 1 | AK108: 1 | AL108: 1
B109: manuLab | M109: 1 | N109: 1 | O109: 1 | P109: 1 | Q109: 1 | R109: 1 | S109: 1 | T109: 1 | U109: 1 | V109: 1 | AB109: 1 | AD109: 1 | AF109: 1 | AG109: 1 | AH109: 1 | AI109: 1 | AJ109: 1 | AK109: 1 | AL109: 1
B110: AEZ1_cropLand | CD110: 1
B111: AEZ2_cropLand | CE111: 1
B112: AEZ3_cropLand | CF112: 1
B113: AEZ4_cropLand | CG113: 1
B114: AEZ5_cropLand | CH114: 1
B115: AEZ6_cropLand | CI115: 1
B116: AEZ7_cropLand | CJ116: 1
B117: AEZ8_cropLand | CK117: 1
B118: AEZ9_cropLand | CL118: 1
B119: AEZ10_cropLand | CM119: 1
B120: AEZ11_cropLand | CN120: 1
B121: AEZ12_cropLand | CO121: 1
B122: AEZ13_cropLand | CP122: 1
B123: AEZ14_cropLand | CQ123: 1
B124: AEZ15_cropLand | CR124: 1
B125: AEZ16_cropLand | CS125: 1
B126: AEZ17_cropLand | CT126: 1
B127: AEZ18_cropLand | CU127: 1
B128: AEZ1_grasLand | CD128: 1
B129: AEZ2_grasLand | CE129: 1
B130: AEZ3_grasLand | CF130: 1
B131: AEZ4_grasLand | CG131: 1
B132: AEZ5_grasLand | CH132: 1
B133: AEZ6_grasLand | CI133: 1
B134: AEZ7_grasLand | CJ134: 1
B135: AEZ8_grasLand | CK135: 1
...

Sheet actPar
B1: Capital | C1: va | D1: va | E1: cap_labsk_ener | F1: cap_labsk_ener | G1: depr | H1: physProd | I1: labor | J1: ener
B2: intensMargElas | C2: Old | D2: New | E2: Old | F2: New | I2: intensMargElas
A3: a-PDR | B3: 0.05 | C3: 0.195804 | D3: 0.522144 | E3: 0.1 | F3: 0.8 | G3: 0.039388125 | H3: 0.31614 | I3: 0.1
A4: a-WHT | B4: 0.05 | C4: 0.195804 | D4: 0.522144 | E4: 0.1 | F4: 0.8 | G4: 0.039388125 | H4: 2436.503 | I4: 0.1
A5: a-GRO | B5: 0.05 | C5: 0.195804 | D5: 0.522144 | E5: 0.1 | F5: 0.8 | G5: 0.039388125 | H5: 1041.321 | I5: 0.1
A6: a-V_F | B6: 0.05 | C6: 0.195804 | D6: 0.522144 | E6: 0.1 | F6: 0.8 | G6: 0.039388125 | I6: 0.1
A7: a-OSD | B7: 0.05 | C7: 0.195804 | D7: 0.522144 | E7: 0.1 | F7: 0.8 | G7: 0.039388125 | I7: 0.1
A8: a-C_B | B8: 0.05 | C8: 0.195804 | D8: 0.522144 | E8: 0.1 | F8: 0.8 | G8: 0.039388125 | I8: 0.1
A9: a-PFB | B9: 0.05 | C9: 0.195804 | D9: 0.522144 | E9: 0.1 | F9: 0.8 | G9: 0.039388125 | H9: 0.026 | I9: 0.1
A10: a-OCR | B10: 0.05 | C10: 0.195804 | D10: 0.522144 | E10: 0.1 | F10: 0.8 | G10: 0.039388125 | I10: 0.1
A11: a-CTL | B11: 0.05 | C11: 0.195804 | D11: 0.522144 | E11: 0.1 | F11: 0.8 | G11: 0.098470312 | H11: 18858.302 | I11: 0.1
A12: a-OAP | B12: 0.05 | C12: 0.195804 | D12: 0.522144 | E12: 0.1 | F12: 0.8 | G12: 0.059082187 | H12: 533.41933 | I12: 0.1
A13: a-RMK | B13: 0.05 | C13: 0.195804 | D13: 0.522144 | E13: 0.1 | F13: 0.8 | G13: 0.098470312 | H13: 3595.4041 | I13: 0.1
A14: a-WOL | B14: 0.05 | C14: 0.195804 | D14: 0.522144 | E14: 0.1 | F14: 0.8 | G14: 0.098470312 | H14: 37.8865 | I14: 0.1
A15: a-FRS | B15: 0.05 | C15: 0.15 | D15: 0.4 | E15: 0.1 | F15: 0.8 | G15: 0.039388125 | I15: 0.1
A16: a-FSH | B16: 0.05 | C16: 0.15 | D16: 0.4 | E16: 0.1 | F16: 0.8 | G16: 0.039388125 | I16: 0.1
A17: a-COA | B17: 0.05 | C17: 0.15 | D17: 0.4 | E17: 0.1 | F17: 0.8 | G17: 0.039388125 | I17: 0.1
A18: a-OIL | B18: 0.05 | C18: 0.15 | D18: 0.4 | E18: 0.1 | F18: 0.8 | G18: 0.039388125 | I18: 0.1
A19: a-GAS | B19: 0.05 | C19: 0.15 | D19: 0.4 | E19: 0.1 | F19: 0.8 | G19: 0.039388125 | I19: 0.1
A20: a-OXT | B20: 0.05 | C20: 0.15 | D20: 0.4 | E20: 0.1 | F20: 0.8 | G20: 0.039388125 | I20: 0.1
A21: a-CMT | B21: 0.05 | C21: 0.74 | D21: 2.24 | E21: 0.1 | F21: 0.8 | G21: 0.039388125 | H21: 510.16535 | I21: 0.1
A22: a-OMT | B22: 0.05 | C22: 0.74 | D22: 2.24 | E22: 0.1 | F22: 0.8 | G22: 0.039388125 | H22: 531.02216 | I22: 0.1
A23: a-VOL | B23: 0.05 | C23: 0.74 | D23: 2.24 | E23: 0.1 | F23: 0.8 | G23: 0.039388125 | I23: 0.1
A24: a-MIL | B24: 0.05 | C24: 0.74 | D24: 2.24 | E24: 0.1 | F24: 0.8 | G24: 0.039388125 | I24: 0.1
A25: a-PCR | B25: 0.05 | C25: 0.74 | D25: 2.24 | E25: 0.1 | F25: 0.8 | G25: 0.039388125 | I25: 0.1
A26: a-SGR | B26: 0.05 | C26: 0.74 | D26: 2.24 | E26: 0.1 | F26: 0.8 | G26: 0.039388125 | I26: 0.1
A27: a-OFD | B27: 0.05 | C27: 0.74 | D27: 2.24 | E27: 0.1 | F27: 0.8 | G27: 0.039388125 | I27: 0.1
A28: a-B_T | B28: 0.05 | C28: 0.74 | D28: 2.24 | E28: 0.1 | F28: 0.8 | G28: 0.039388125 | I28: 0.1
A29: a-TEX | B29: 0.05 | C29: 0.85 | D29: 2.52 | E29: 0.1 | F29: 0.8 | G29: 0.039388125 | I29: 0.1
A30: a-WAP | B30: 0.05 | C30: 0.85 | D30: 2.52 | E30: 0.1 | F30: 0.8 | G30: 0.039388125 | I30: 0.1
A31: a-LEA | B31: 0.05 | C31: 0.85 | D31: 2.52 | E31: 0.1 | F31: 0.8 | G31: 0.039388125 | I31: 0.1
A32: a-LUM | B32: 0.05 | C32: 0.85 | D32: 2.52 | E32: 0.1 | F32: 0.8 | G32: 0.039388125 | I32: 0.1
A33: a-PPP | B33: 0.05 | C33: 0.85 | D33: 2.52 | E33: 0.1 | F33: 0.8 | G33: 0.039388125 | I33: 0.1
A34: a-P_C | B34: 0.05 | C34: 0.85 | D34: 2.52 | E34: 0.1 | F34: 0.8 | G34: 0.039388125 | I34: 0.1
... A64: a-AFS | B64: 0.05 | C64: 1.26 | D64: 3.36 | E64: 0.1 | F64: 0.8 | G64: 0.039388125 | I64: 0.1
A65: a-OTP | B65: 0.05 | C65: 1.26 | D65: 3.36 | E65: 0.1 | F65: 0.8 | G65: 0.039388125 | I65: 0.1 | J65: Eps
A66: a-WTP | B66: 0.05 | C66: 1.26 | D66: 3.36 | E66: 0.1 | F66: 0.8 | G66: 0.039388125 | I66: 0.1
A67: a-ATP | B67: 0.05 | C67: 1.26 | D67: 3.36 | E67: 0.1 | F67: 0.8 | G67: 0.039388125 | I67: 0.1
A68: a-WHS | B68: 0.05 | C68: 1.26 | D68: 3.36 | E68: 0.1 | F68: 0.8 | G68: 0.039388125 | I68: 0.1
A69: a-CMN | B69: 0.05 | C69: 0.85 | D69: 2.52 | E69: 0.1 | F69: 0.8 | G69: 0.039388125 | I69: 0.1
A70: a-OFI | B70: 0.05 | C70: 0.85 | D70: 2.52 | E70: 0.1 | F70: 0.8 | G70: 0.039388125 | I70: 0.1
A71: a-INS | B71: 0.05 | C71: 0.85 | D71: 2.52 | E71: 0.1 | F71: 0.8 | G71: 0.039388125 | I71: 0.1
A72: a-RSA | B72: 0.05 | C72: 0.85 | D72: 2.52 | E72: 0.1 | F72: 0.8 | G72: 0.039388125 | I72: 0.1
A73: a-OBS | B73: 0.05 | C73: 0.85 | D73: 2.52 | E73: 0.1 | F73: 0.8 | G73: 0.039388125 | I73: 0.1
A74: a-ROS | B74: 0.05 | C74: 0.85 | D74: 2.52 | E74: 0.1 | F74: 0.8 | G74: 0.039388125 | I74: 0.1
A75: a-OSG | B75: 0.05 | C75: 0.85 | D75: 2.52 | E75: 0.1 | F75: 0.8 | G75: 0.039388125 | I75: 0.1
A76: a-EDU | B76: 0.05 | C76: 0.85 | D76: 2.52 | E76: 0.1 | F76: 0.8 | G76: 0.039388125 | I76: 0.1
A77: a-HHT | B77: 0.05 | C77: 0.85 | D77: 2.52 | E77: 0.1 | F77: 0.8 | G77: 0.039388125 | I77: 0.1
A78: a-DWE | B78: 0.05 | C78: 0.85 | D78: 2.52 | E78: 0.1 | F78: 0.8 | G78: 0.039388125 | I78: 0.1
A79: a-ctlRais | B79: 0.05 | C79: 0.195804 | D79: 0.522144 | E79: 0.1 | F79: 0.8 | G79: 0.098470312 | H79: 14185.488 | I79: 0.1
A80: a-otpEle | B80: 0.05 | C80: 1.26 | D80: 3.36 | E80: 0.1 | F80: 0.8 | G80: 0.039388125 | I80: 0.1 | J80: Eps
A81: a-macc | B81: 0.05 | C81: 0.85 | D81: 2.52 | E81: 0.1 | F81: 0.8 | G81: 0.04075154 | I81: 0.1

Sheet comPar
B1: sigmas0 | C1: sigmam0 | D1: omegax0 | E1: sigmamg0 | F1: omegam0 | G1: etae0 | H1: alphaST0 | I1: rhoPDelSt0 | J1: rhoXDelSt0
A2: c-pdr | C2: 5.05 | D2: 5.05 | H2: 0.4
A3: c-wht | C3: 4.45 | D3: 4.45 | H3: 0.4
A4: c-gro | C4: 1.3 | D4: 1.3 | H4: 0.4
A5: c-v_f | C5: 1.85 | D5: 1.85 | H5: 0.4
A6: c-osd | C6: 2.45 | D6: 2.45 | H6: 0.4
A7: c-c_b | C7: 2.7 | D7: 2.7 | H7: 0.4
A8: c-pfb | C8: 2.5 | D8: 2.5 | H8: 0.4
A9: c-ocr | C9: 3.25 | D9: 3.25 | H9: 0.4
A10: c-ctl | C10: 2 | D10: 2
A11: c-oap | C11: 1.3 | D11: 1.3
A12: c-rmk | C12: 3.65 | D12: 3.65
A13: c-wol | C13: 6.45 | D13: 6.45
A14: c-frs | C14: 2.5 | D14: 2.5
A15: c-fsh | C15: 1.25 | D15: 1.25
A16: c-coa | C16: 3.05 | D16: 3.05
A17: c-oil | C17: 5.2 | D17: 5.2
A18: c-gas | C18: 10 | D18: 10 | M18: original: 17.5
A19: c-oxt | C19: 0.9 | D19: 0.9
A20: c-cmt | C20: 3.85 | D20: 3.85
A21: c-omt | C21: 4.4 | D21: 4.4
A22: c-vol | C22: 3.3 | D22: 3.3
A23: c-mil | C23: 3.65 | D23: 3.65
A24: c-pcr | C24: 2.6 | D24: 2.6
A25: c-sgr | C25: 2.7 | D25: 2.7
A26: c-ofd | C26: 2 | D26: 2
A27: c-b_t | C27: 1.15 | D27: 1.15
A28: c-tex | C28: 3.75 | D28: 3.75
A29: c-wap | C29: 3.7 | D29: 3.7
A30: c-lea | C30: 4.05 | D30: 4.05
... A46: c-omf | C46: 3.75 | D46: 3.75
A47: c-TnD | B47: 5 | C47: 2.8 | D47: 2.8
A48: c-ely | B48: 5 | C48: 2.8 | D48: 2.8
A49: c-gdt | C49: 2.8 | D49: 2.8
A50: c-wtr | C50: 2.8 | D50: 2.8
A51: c-cns | C51: 1.9 | D51: 1.9
A52: c-trd | C52: 1.9 | D52: 1.9
A53: c-afs | C53: 1.9 | D53: 1.9
A54: c-otp | B54: 2 | C54: 1.9 | D54: 1.9 | G54: 10
A55: c-wtp | C55: 1.9 | D55: 1.9
A56: c-atp | C56: 1.9 | D56: 1.9
A57: c-whs | C57: 1.9 | D57: 1.9
A58: c-cmn | C58: 1.9 | D58: 1.9
A59: c-ofi | C59: 1.9 | D59: 1.9
A60: c-ins | C60: 1.9 | D60: 1.9
A61: c-rsa | C61: 1.9 | D61: 1.9
A62: c-obs | C62: 1.9 | D62: 1.9
A63: c-ros | C63: 1.9 | D63: 1.9
A64: c-osg | C64: 1.9 | D64: 1.9
A65: c-edu | C65: 1.9 | D65: 1.9
A66: c-hht | C66: 1.9 | D66: 1.9
A67: c-dwe | C67: 1.9 | D67: 1.9

Sheet hohPar
B1: Estimated regresion function for GTAP incp and subp parameters of CDE demand system as a function of log(GDP)
C3: Crops | D3: MeatDairy | E3: FoodOther | F3: Clothing | G3: Manu | H3: HousEner | I3: Hot_Trad | J3: Serv | K3: Trans
A4: incp | B4: logGdp | C4: -0.35989833 | D4: -0.2626742 | E4: -0.2535079 | F4: -0.26211887 | G4: -0.0038737402 | H4: -0.12280265 | I4: -0.48752412 | J4: -0.32878554 | K4: -0.22094564
A5: incp | B5: constant | C5: 1.6029705 | D5: 1.6297386 | E5: 1.4684957 | F5: 1.6155831 | G5: 1.0268112 | H5: 1.5567056 | I5: 3.3439665 | J5: 2.5574108 | K5: 1.8364509
A6: subP | B6: logGdp | C6: 0.078237188 | D6: -0.28871033 | E6: -0.2565631 | F6: -0.28728804 | G6: -0.35529065 | H6: -0.33566719 | I6: -0.28736376 | J6: -0.30851208 | K6: -0.32077306
A7: subP | B7: constant | C7: 0.62104646 | D7: 1.7137944 | E7: 1.6471096 | F7: 1.7118797 | G7: 1.8671344 | H7: 1.7781962 | I7: 1.5435341 | J7: 1.6471142 | K7: 1.7411171
C9: incElas0 | D9: incElas0 | E9: incElas0 | F9: incElas0 | G9: incElas0 | H9: incElas0 | I9: incElas0 | J9: incElas0 | K9: incElas0 | L9: prcElas0 | M9: prcElas0 | N9: prcElas0 | O9: prcElas0 | P9: prcElas0 | Q9: prcElas0 | R9: prcElas0 | S9: prcElas0 | T9: prcElas0
C10: Crops | D10: MeatDairy | E10: FoodOther | F10: Clothing | G10: Manu | H10: Hot_Trad | I10: Serv | J10: Trans | K10: HousEner | L10: Crops | M10: MeatDairy | N10: FoodOther | O10: Clothing | P10: Manu | Q10: Hot_Trad | R10: Serv | S10: Trans | T10: HousEner
B11: h-hhold | C11: 0.56315219 | D11: 0.92774559 | E11: 0.81472831 | F11: 0.93786425 | G11: 1.3737874 | H11: 1.7935606 | I11: 1.8270159 | J11: 1.3449195 | K11: 1.4785995 | L11: -0.28397399 | M11: -0.35312015 | N11: -0.33605066 | O11: -0.29809809 | P11: -0.49986561 | Q11: -0.5487725 | R11: -0.48875358 | S11: -0.50568309 | T11: -0.44654557

Sheet GDPComposition
C1: 2017 | D1: 2018 | E1: 2019 | F1: 2020 | G1: 2021 | H1: 2022 | I1: 2023 | J1: 2024 | K1: 2025 | L1: 2026 | M1: 2027 | N1: 2028 | O1: 2029 | P1: 2030 | Q1: 2031 | R1: 2032 | S1: 2033 | T1: 2034 | U1: 2035 | V1: 2036 | W1: 2037 | X1: 2038 | Y1: 2039 | Z1: 2040 | AA1: 2041 | AB1: 2042 | AC1: 2043 | AD1: 2044 | AE1: 2045 | AF1: 2046 | AG1: 2047 | AH1: 2048 | AI1: 2049 | AJ1: 2050 | AK1: 2051 | AL1: 2052 | AM1: 2053 | AN1: 2054 | AO1: 2055 | AP1: 2056 | AQ1: 2057 | AR1: 2058 | AS1: 2059 | AT1: 2060 | AU1: 2061 | AV1: 2062 | AW1: 2063 | AX1: 2064 | AY1: 2065 | AZ1: 2066 | BA1: 2067 | BB1: 2068 | BC1: 2069 | BD1: 2070 | BE1: 2071 | BF1: 2072 | BG1: 2073 | BH1: 2074 | BI1: 2075 | BJ1: 2076 | BK1: 2077 | BL1: 2078 | BM1: 2079 | BN1: 2080 | BO1: 2081 | BP1: 2082 | BQ1: 2083 | BR1: 2084 | BS1: 2085 | BT1: 2086 | BU1: 2087 | BV1: 2088 | BW1: 2089 | BX1: 2090 | BY1: 2091 | BZ1: 2092 | CA1: 2093 | CB1: 2094 | CC1: 2095 | CD1: 2096 | CE1: 2097 | CF1: 2098 | CG1: 2099 | CH1: 2100
A2: bas | B2: GDP | C2: 1.3 | D2: 1.1 | E2: 1 | F2: -5.1 | G2: 3.8535559 | H2: 3.2060224 | I2: 1.2773302 | J2: 1.3759786 | K2: 8.08649 | L2: 7.1835829 | M2: 6.3442614 | N2: 5.7274145 | O2: 5.3119461 | P2: 5.0224433 | Q2: 4.7203568 | R2: 4.5720469 | S2: 4.436316 | T2: 4.2797046 | U2: 4.1210674 | V2: 3.9545431 | W2: 3.8381797 | X2: 3.7279799 | Y2: 3.646175 | Z2: 3.5747681 | AA2: 3.470516 | AB2: 3.4142941 | AC2: 3.3572383 | AD2: 3.3081737 | AE2: 3.2665263 | AF2: 3.2004522 | AG2: 3.1709637 | AH2: 3.1441552 | AI2: 3.1216965 | AJ2: 3.1088884 | AK2: 3.1043498 | AL2: 3.1000384 | AM2: 3.0959207 | AN2: 3.0919717 | AO2: 3.0881728 | AP2: 3.08451 | AQ2: 3.0809724 | AR2: 3.0775519 | AS2: 3.0742419 | AT2: 3.0710369 | AU2: 3.0679324 | AV2: 3.0649245 | AW2: 3.0620096 | AX2: 3.0591845 | AY2: 3.0564463 | AZ2: 3.053792 | BA2: 3.051219 | BB2: 3.0487246 | BC2: 3.0463063 | BD2: 3.0439617 | BE2: 3.0416885 | BF2: 3.0394844 | BG2: 3.0373472 | BH2: 3.0352748 | BI2: 3.0332652 | BJ2: 3.0313164 | BK2: 3.0294265 | BL2: 3.0275937 | BM2: 3.0258162 | BN2: 3.0240923 | BO2: 3.0224204 | BP2: 3.0207989 | BQ2: 3.0192262 | BR2: 3.0177009 | BS2: 3.0162215 | BT2: 3.0147866 | BU2: 3.0133948 | BV2: 3.0120449 | BW2: 3.0107356 | BX2: 3.0094657 | BY2: 3.0082339 | BZ2: 3.0070392 | CA2: 3.0058803 | CB2: 3.0047563 | CC2: 3.003666 | CD2: 3.0026085 | CE2: 3.0015827 | CF2: 3.0005878 | CG2: 2.9996227 | CH2: 2.9986866
A3: bas | B3: GovCons | C3: 0.18268518 | D3: 0.18268518 | E3: 0.18268518 | F3: 0.18268518 | G3: 0.18268518 | H3: 0.18268518 | I3: 0.18268518 | J3: 0.18268518 | K3: 0.18268518 | L3: 0.18268518 | M3: 0.18268518 | N3: 0.18268518 | O3: 0.18268518 | P3: 0.18268518 | Q3: 0.18268518 | R3: 0.18268518 | S3: 0.18268518 | T3: 0.18268518 | U3: 0.18268518 | V3: 0.18268518 | W3: 0.18268518 | X3: 0.18268518 | Y3: 0.18268518 | Z3: 0.18268518 | AA3: 0.18268518 | AB3: 0.18268518 | AC3: 0.18268518 | AD3: 0.18268518 | AE3: 0.18268518 | AF3: 0.18268518 | AG3: 0.18268518 | AH3: 0.18268518 | AI3: 0.18268518 | AJ3: 0.18268518 | AK3: 0.18268518 | AL3: 0.18268518 | AM3: 0.18268518 | AN3: 0.18268518 | AO3: 0.18268518 | AP3: 0.18268518 | AQ3: 0.18268518 | AR3: 0.18268518 | AS3: 0.18268518 | AT3: 0.18268518 | AU3: 0.18268518 | AV3: 0.18268518 | AW3: 0.18268518 | AX3: 0.18268518 | AY3: 0.18268518 | AZ3: 0.18268518 | BA3: 0.18268518 | BB3: 0.18268518 | BC3: 0.18268518 | BD3: 0.18268518 | BE3: 0.18268518 | BF3: 0.18268518 | BG3: 0.18268518 | BH3: 0.18268518 | BI3: 0.18268518 | BJ3: 0.18268518 | BK3: 0.18268518 | BL3: 0.18268518 | BM3: 0.18268518 | BN3: 0.18268518 | BO3: 0.18268518 | BP3: 0.18268518 | BQ3: 0.18268518 | BR3: 0.18268518 | BS3: 0.18268518 | BT3: 0.18268518 | BU3: 0.18268518 | BV3: 0.18268518 | BW3: 0.18268518 | BX3: 0.18268518 | BY3: 0.18268518 | BZ3: 0.18268518 | CA3: 0.18268518 | CB3: 0.18268518 | CC3: 0.18268518 | CD3: 0.18268518 | CE3: 0.18268518 | CF3: 0.18268518 | CG3: 0.18268518 | CH3: 0.18268518
A4: bas | B4: netExp | C4: 0.013443579 | D4: 0.013443579 | E4: 0.013443579 | F4: 0.013443579 | G4: 0.013443579 | H4: 0.013443579 | I4: 0.013443579 | J4: 0.013443579 | K4: 0.013443579 | L4: 0.013443579 | M4: 0.013443579 | N4: 0.013443579 | O4: 0.013443579 | P4: 0.013443579 | Q4: 0.013443579 | R4: 0.013443579 | S4: 0.013443579 | T4: 0.013443579 | U4: 0.013443579 | V4: 0.013443579 | W4: 0.013443579 | X4: 0.013443579 | Y4: 0.013443579 | Z4: 0.013443579 | AA4: 0.013443579 | AB4: 0.013443579 | AC4: 0.013443579 | AD4: 0.013443579 | AE4: 0.013443579 | AF4: 0.013443579 | AG4: 0.013443579 | AH4: 0.013443579 | AI4: 0.013443579 | AJ4: 0.013443579 | AK4: 0.013443579 | AL4: 0.013443579 | AM4: 0.013443579 | AN4: 0.013443579 | AO4: 0.013443579 | AP4: 0.013443579 | AQ4: 0.013443579 | AR4: 0.013443579 | AS4: 0.013443579 | AT4: 0.013443579 | AU4: 0.013443579 | AV4: 0.013443579 | AW4: 0.013443579 | AX4: 0.013443579 | AY4: 0.013443579 | AZ4: 0.013443579 | BA4: 0.013443579 | BB4: 0.013443579 | BC4: 0.013443579 | BD4: 0.013443579 | BE4: 0.013443579 | BF4: 0.013443579 | BG4: 0.013443579 | BH4: 0.013443579 | BI4: 0.013443579 | BJ4: 0.013443579 | BK4: 0.013443579 | BL4: 0.013443579 | BM4: 0.013443579 | BN4: 0.013443579 | BO4: 0.013443579 | BP4: 0.013443579 | BQ4: 0.013443579 | BR4: 0.013443579 | BS4: 0.013443579 | BT4: 0.013443579 | BU4: 0.013443579 | BV4: 0.013443579 | BW4: 0.013443579 | BX4: 0.013443579 | BY4: 0.013443579 | BZ4: 0.013443579 | CA4: 0.013443579 | CB4: 0.013443579 | CC4: 0.013443579 | CD4: 0.013443579 | CE4: 0.013443579 | CF4: 0.013443579 | CG4: 0.013443579 | CH4: 0.013443579
A5: bas | B5: savf | C5: -0.015235255 | D5: -0.015235255 | E5: -0.015235255 | F5: -0.015235255 | G5: -0.015235255 | H5: -0.015235255 | I5: -0.015235255 | J5: -0.015235255 | K5: -0.015235255 | L5: -0.015235255 | M5: -0.015235255 | N5: -0.015235255 | O5: -0.015235255 | P5: -0.015235255 | Q5: -0.015235255 | R5: -0.015235255 | S5: -0.015235255 | T5: -0.015235255 | U5: -0.015235255 | V5: -0.015235255 | W5: -0.015235255 | X5: -0.015235255 | Y5: -0.015235255 | Z5: -0.015235255 | AA5: -0.015235255 | AB5: -0.015235255 | AC5: -0.015235255 | AD5: -0.015235255 | AE5: -0.015235255 | AF5: -0.015235255 | AG5: -0.015235255 | AH5: -0.015235255 | AI5: -0.015235255 | AJ5: -0.015235255 | AK5: -0.015235255 | AL5: -0.015235255 | AM5: -0.015235255 | AN5: -0.015235255 | AO5: -0.015235255 | AP5: -0.015235255 | AQ5: -0.015235255 | AR5: -0.015235255 | AS5: -0.015235255 | AT5: -0.015235255 | AU5: -0.015235255 | AV5: -0.015235255 | AW5: -0.015235255 | AX5: -0.015235255 | AY5: -0.015235255 | AZ5: -0.015235255 | BA5: -0.015235255 | BB5: -0.015235255 | BC5: -0.015235255 | BD5: -0.015235255 | BE5: -0.015235255 | BF5: -0.015235255 | BG5: -0.015235255 | BH5: -0.015235255 | BI5: -0.015235255 | BJ5: -0.015235255 | BK5: -0.015235255 | BL5: -0.015235255 | BM5: -0.015235255 | BN5: -0.015235255 | BO5: -0.015235255 | BP5: -0.015235255 | BQ5: -0.015235255 | BR5: -0.015235255 | BS5: -0.015235255 | BT5: -0.015235255 | BU5: -0.015235255 | BV5: -0.015235255 | BW5: -0.015235255 | BX5: -0.015235255 | BY5: -0.015235255 | BZ5: -0.015235255 | CA5: -0.015235255 | CB5: -0.015235255 | CC5: -0.015235255 | CD5: -0.015235255 | CE5: -0.015235255 | CF5: -0.015235255 | CG5: -0.015235255 | CH5: -0.015235255

Sheet EnTech
A1: size of stepping on toes effect | D1: supernormal growth | G1: Varia
A2: larger value = smaller R&D response to change in revenue; 1 = no response; no value = R&D mechanism is switched off | D2: difference between the productivity growth of the sector and the balanced growth path of the economy; 0 = the sector does not grow faster
A3: PhiRDtoes | D3: Supfgrowth
A5: a-solarP | B5: 0.3 | D5: a-solarP | E5: 0.02 | G5: PrvRD | H5: 0.02 | J5: Private R&D share of GDP
A6: a-windBL | B6: 0.3 | D6: a-windBL | E6: 0.02 | G6: rhoEn | H6: 0.06 | J6: fraction of innovations that go to inventions (inventions are not bounded by the frontier)
G7: sigmaxpvt | H7: 0.5 | J7: elasticity of substitution between processes
G8: obsol | H8: 0.2 | J8: baseyear obsolescence rate
G9: fgrowthDef | H9: 0.01 | J9: growth of the frontier
G10: interestRD | H10: 0.03 | J10: interest rate considered by the R&D firms
A14: a-coalP | B14: 0.3
A15: a-gasP | B15: 0.3
A16: a-otherP | B16: 0.3
A17: a-NuclearP | B17: 0.3
A18: a-nmm | B18: 0.3
A19: a-i_s | B19: 0.3

Sheet othPar
B1: sigmaf0
A2: g-govt
A3: i-CGDS
A4: i-ginv

Sheet GHGMitigation
C1: 2017 | D1: =+C1+1 -> 2018 | E1: =+D1+1 -> 2019 | F1: =+E1+1 -> 2020 | G1: =+F1+1 -> 2021 | H1: =+G1+1 -> 2022 | I1: =+H1+1 -> 2023 | J1: =+I1+1 -> 2024 | K1: =+J1+1 -> 2025 | ... CH1: =+CG1+1 -> 2100
A2: BAU | B2: carbonTax | C2: 0.5 | D2: =+C2+0.5 -> 1 | E2: =+D2+0.5 -> 1.5 | F2: =+E2+0.5 -> 2 | G2: =+F2+0.5 -> 2.5 | H2: =+G2+0.5 -> 3 | I2: =+H2+0.5 -> 3.5 | J2: =+I2+0.5 -> 4 | K2: =+J2+0.5 -> 4.5 | ... CH2: =+CG2+0.5 -> 42
A3: BAU | B3: ceilingBench | C3: 1 | D3: =+MAX(+C3-0.02,0.0000000001) -> 0.98 | E3: =+MAX(+D3-0.02,0.0000000001) -> 0.96 | F3: =+MAX(+E3-0.02,0.0000000001) -> 0.94 | G3: =+MAX(+F3-0.02,0.0000000001) -> 0.92 | H3: =+MAX(+G3-0.02,0.0000000001) -> 0.9 | I3: =+MAX(+H3-0.02,0.0000000001) -> 0.88 | J3: =+MAX(+I3-0.02,0.0000000001) -> 0.86 | K3: =+MAX(+J3-0.02,0.0000000001) -> 0.84 | ... CH3: =+MAX(+CG3-0.02,0.0000000001) -> 1e-10
A4: BAU | B4: ceilingBaseline | C4: 1 | D4: =+MAX(+C4-0.02,0.0000000001) -> 0.98 | E4: =+MAX(+D4-0.02,0.0000000001) -> 0.96 | F4: =+MAX(+E4-0.02,0.0000000001) -> 0.94 | G4: =+MAX(+F4-0.02,0.0000000001) -> 0.92 | H4: =+MAX(+G4-0.02,0.0000000001) -> 0.9 | I4: =+MAX(+H4-0.02,0.0000000001) -> 0.88 | J4: =+MAX(+I4-0.02,0.0000000001) -> 0.86 | K4: =+MAX(+J4-0.02,0.0000000001) -> 0.84 | ... CH4: =+MAX(+CG4-0.02,0.0000000001) -> 1e-10
A5: BAU | B5: ceilingAbsolute

Sheet Energy
D1: 2017 | E1: 2018 | F1: 2019 | G1: 2020 | H1: 2021 | I1: 2022 | J1: 2023 | K1: 2024 | L1: 2025 | M1: 2026 | N1: 2027 | O1: 2028 | P1: 2029 | Q1: 2030 | R1: 2031 | S1: 2032 | T1: 2033 | U1: 2034 | V1: 2035 | W1: 2036 | X1: 2037 | Y1: 2038 | Z1: 2039 | AA1: 2040 | AB1: 2041 | AC1: 2042 | AD1: 2043 | AE1: 2044 | AF1: 2045 | AG1: 2046 | AH1: 2047 | AI1: 2048 | AJ1: 2049 | AK1: 2050 | AL1: 2051 | AM1: 2052 | AN1: 2053 | AO1: 2054 | AP1: 2055 | AQ1: 2056 | AR1: 2057 | AS1: 2058 | AT1: 2059 | AU1: 2060 | AV1: 2061 | AW1: 2062 | AX1: 2063 | AY1: 2064 | AZ1: 2065 | BA1: 2066 | BB1: 2067 | BC1: 2068 | BD1: 2069 | BE1: 2070 | BF1: 2071 | BG1: 2072 | BH1: 2073 | BI1: 2074 | BJ1: 2075 | BK1: 2076 | BL1: 2077 | BM1: 2078 | BN1: 2079 | BO1: 2080 | BP1: 2081 | BQ1: 2082 | BR1: 2083 | BS1: 2084 | BT1: 2085 | BU1: 2086 | BV1: 2087 | BW1: 2088 | BX1: 2089 | BY1: 2090 | BZ1: 2091 | CA1: 2092 | CB1: 2093 | CC1: 2094 | CD1: 2095 | CE1: 2096 | CF1: 2097 | CG1: 2098 | CH1: 2099 | CI1: 2100
A2: BAU | B2: c-OIL | C2: a-OTP | D2: 1 | E2: 1.0062573 | F2: 1.0112965 | G2: 0.93927848 | H2: 0.97747314 | I2: 1.0093121 | J2: 1.0178641 | K2: 1.0277433 | L2: 1.1238944 | M2: 1.2163612 | N2: 1.3036788 | O2: 1.3872163 | P2: 1.4689051 | Q2: 1.5500906 | R2: 1.6299122 | S2: 1.7108237 | T2: 1.7928501 | U2: 1.8753009 | V2: 1.9578263 | W2: 2.0399096 | X2: 2.1224682 | Y2: 2.2054455 | Z2: 2.2894124 | AA2: 2.3745335 | AB2: 2.4597261 | AC2: 2.5462473 | AD2: 2.6339966 | AE2: 2.7231551 | AF2: 2.8139144 | AG2: 2.9053753 | AH2: 2.9987385 | AI2: 3.0940974 | AJ2: 3.1916203 | AK2: 3.2917063 | AL2: 3.3947443 | AM2: 3.5008246 | AN2: 3.6100397 | AO2: 3.7224838 | AP2: 3.8382536 | AQ2: 3.9574482 | AR2: 4.0801693 | AS2: 4.2065217 | AT2: 4.3366129 | AU2: 4.4705537 | AV2: 4.6084579 | AW2: 4.7504428 | AX2: 4.8966293 | AY2: 5.0471415 | AZ2: 5.2021075 | BA2: 5.361659 | BB2: 5.5259316 | BC2: 5.6950651 | BD2: 5.8692031 | BE2: 6.0484939 | BF2: 6.2330897 | BG2: 6.4231477 | BH2: 6.6188293 | BI2: 6.8203009 | BJ2: 7.0277339 | BK2: 7.2413047 | BL2: 7.4611948 | BM2: 7.6875913 | BN2: 7.9206866 | BO2: 8.160679 | BP2: 8.4077725 | BQ2: 8.6621773 | BR2: 8.9241097 | BS2: 9.1937925 | BT2: 9.4714551 | BU2: 9.7573336 | BV2: 10.051671 | BW2: 10.354718 | BX2: 10.666732 | BY2: 10.987978 | BZ2: 11.318731 | CA2: 11.65927 | CB2: 12.009886 | CC2: 12.370877 | CD2: 12.742551 | CE2: 13.125222 | CF2: 13.519217 | CG2: 13.924871 | CH2: 14.34253 | CI2: 14.772547
A3: BAU | B3: c-OIL | C3: a-WTP | D3: 1 | E3: 1.007359 | F3: 1.0136867 | G3: 0.9534183 | H3: 0.98872571 | I3: 1.0184412 | J3: 1.0278822 | K3: 1.0385034 | L3: 1.1243339 | M3: 1.2063182 | N3: 1.2833697 | O3: 1.3568117 | P3: 1.4283816 | Q3: 1.4992706 | R3: 1.5687969 | S3: 1.6390401 | T3: 1.710031 | U3: 1.7812107 | V3: 1.8523082 | W3: 1.9229195 | X3: 1.9938113 | Y3: 2.0649489 | Z3: 2.1368042 | AA3: 2.2095156 | AB3: 2.282219 | AC3: 2.3559319 | AD3: 2.4305771 | AE3: 2.5063021 | AF3: 2.5832616 | AG3: 2.6607449 | AH3: 2.7397066 | AI3: 2.8202202 | AJ3: 2.9024173 | AK3: 2.9866095 | AL3: 3.0730979 | AM3: 3.161948 | AN3: 3.2532267 | AO3: 3.347002 | AP3: 3.4433434 | AQ3: 3.5423219 | AR3: 3.6440106 | AS3: 3.7484841 | AT3: 3.8558191 | AU3: 3.9660944 | AV3: 4.0793909 | AW3: 4.1957916 | AX3: 4.3153818 | AY3: 4.4382493 | AZ3: 4.5644841 | BA3: 4.6941788 | BB3: 4.8274285 | BC3: 4.9643308 | BD3: 5.1049862 | BE3: 5.2494978 | BF3: 5.3979717 | BG3: 5.5505167 | BH3: 5.7072447 | BI3: 5.8682708 | BJ3: 6.033713 | BK3: 6.2036928 | BL3: 6.3783348 | BM3: 6.5577672 | BN3: 6.7421218 | BO3: 6.9315337 | BP3: 7.1261421 | BQ3: 7.3260897 | BR3: 7.5315234 | BS3: 7.7425939 | BT3: 7.9594562 | BU3: 8.1822695 | BV3: 8.4111974 | BW3: 8.6464081 | BX3: 8.8880742 | BY3: 9.1363731 | BZ3: 9.3914874 | CA3: 9.6536042 | CB3: 9.9229162 | CC3: 10.199621 | CD3: 10.483922 | CE3: 10.776028 | CF3: 11.076154 | CG3: 11.38452 | CH3: 11.701353 | CI3: 12.026885
A4: BAU | B4: c-OIL | C4: a-ATP | D4: 1 | E4: 1.0098086 | F4: 1.018492 | G4: 0.95209688 | H4: 0.99314845 | I4: 1.0281908 | J4: 1.0404815 | K4: 1.0541608 | L4: 1.1535899 | M4: 1.2497978 | N4: 1.3413402 | O4: 1.4295791 | P4: 1.5164381 | Q4: 1.6032639 | R4: 1.6892025 | S4: 1.7767171 | T4: 1.8658485 | U4: 1.9559166 | V4: 2.0465791 | W4: 2.1373216 | X4: 2.229079 | Y4: 2.3218042 | Z4: 2.416089 | AA4: 2.5121156 | AB4: 2.6087908 | AC4: 2.7074122 | AD4: 2.8078932 | AE4: 2.9104369 | AF4: 3.0152592 | AG4: 3.1214468 | AH4: 3.2302606 | AI4: 3.3418201 | AJ4: 3.4563245 | AK4: 3.5742167 | AL4: 3.695934 | AM4: 3.8216035 | AN4: 3.9513556 | AO4: 4.0853244 | AP4: 4.2236476 | AQ4: 4.3664671 | AR4: 4.5139291 | AS4: 4.6661843 | AT4: 4.8233883 | AU4: 4.9857014 | AV4: 5.1532894 | AW4: 5.3263232 | AX4: 5.5049791 | AY4: 5.6894394 | AZ4: 5.8798921 | BA4: 6.0765314 | BB4: 6.2795578 | BC4: 6.489178 | BD4: 6.7056059 | BE4: 6.9290619 | BF4: 7.1597738 | BG4: 7.3979766 | BH4: 7.6439131 | BI4: 7.8978338 | BJ4: 8.1599974 | BK4: 8.430671 | BL4: 8.7101303 | BM4: 8.9986601 | BN4: 9.2965541 | BO4: 9.6041158 | BP4: 9.9216585 | BQ4: 10.249505 | BR4: 10.587991 | BS4: 10.937459 | BT4: 11.298266 | BU4: 11.670779 | BV4: 12.055378 | BW4: 12.452455 | BX4: 12.862412 | BY4: 13.285669 | BZ4: 13.722656 | CA4: 14.173817 | CB4: 14.639613 | CC4: 15.120517 | CD4: 15.617019 | CE4: 16.129625 | CF4: 16.658856 | CG4: 17.205251 | CH4: 17.769367 | CI4: 18.351778
A5: BAU | B5: c-P_C | C5: a-OTP | D5: 1 | E5: 1.0062573 | F5: 1.0112965 | G5: 0.93927848 | H5: 0.97747314 | I5: 1.0093121 | J5: 1.0178641 | K5: 1.0277433 | L5: 1.1238944 | M5: 1.2163612 | N5: 1.3036788 | O5: 1.3872163 | P5: 1.4689051 | Q5: 1.5500906 | R5: 1.6299122 | S5: 1.7108237 | T5: 1.7928501 | U5: 1.8753009 | V5: 1.9578263 | W5: 2.0399096 | X5: 2.1224682 | Y5: 2.2054455 | Z5: 2.2894124 | AA5: 2.3745335 | AB5: 2.4597261 | AC5: 2.5462473 | AD5: 2.6339966 | AE5: 2.7231551 | AF5: 2.8139144 | AG5: 2.9053753 | AH5: 2.9987385 | AI5: 3.0940974 | AJ5: 3.1916203 | AK5: 3.2917063 | AL5: 3.3947443 | AM5: 3.5008246 | AN5: 3.6100397 | AO5: 3.7224838 | AP5: 3.8382536 | AQ5: 3.9574482 | AR5: 4.0801693 | AS5: 4.2065217 | AT5: 4.3366129 | AU5: 4.4705537 | AV5: 4.6084579 | AW5: 4.7504428 | AX5: 4.8966293 | AY5: 5.0471415 | AZ5: 5.2021075 | BA5: 5.361659 | BB5: 5.5259316 | BC5: 5.6950651 | BD5: 5.8692031 | BE5: 6.0484939 | BF5: 6.2330897 | BG5: 6.4231477 | BH5: 6.6188293 | BI5: 6.8203009 | BJ5: 7.0277339 | BK5: 7.2413047 | BL5: 7.4611948 | BM5: 7.6875913 | BN5: 7.9206866 | BO5: 8.160679 | BP5: 8.4077725 | BQ5: 8.6621773 | BR5: 8.9241097 | BS5: 9.1937925 | BT5: 9.4714551 | BU5: 9.7573336 | BV5: 10.051671 | BW5: 10.354718 | BX5: 10.666732 | BY5: 10.987978 | BZ5: 11.318731 | CA5: 11.65927 | CB5: 12.009886 | CC5: 12.370877 | CD5: 12.742551 | CE5: 13.125222 | CF5: 13.519217 | CG5: 13.924871 | CH5: 14.34253 | CI5: 14.772547
A6: BAU | B6: c-P_C | C6: a-WTP | D6: 1 | E6: 1.007359 | F6: 1.0136867 | G6: 0.9534183 | H6: 0.98872571 | I6: 1.0184412 | J6: 1.0278822 | K6: 1.0385034 | L6: 1.1243339 | M6: 1.2063182 | N6: 1.2833697 | O6: 1.3568117 | P6: 1.4283816 | Q6: 1.4992706 | R6: 1.5687969 | S6: 1.6390401 | T6: 1.710031 | U6: 1.7812107 | V6: 1.8523082 | W6: 1.9229195 | X6: 1.9938113 | Y6: 2.0649489 | Z6: 2.1368042 | AA6: 2.2095156 | AB6: 2.282219 | AC6: 2.3559319 | AD6: 2.4305771 | AE6: 2.5063021 | AF6: 2.5832616 | AG6: 2.6607449 | AH6: 2.7397066 | AI6: 2.8202202 | AJ6: 2.9024173 | AK6: 2.9866095 | AL6: 3.0730979 | AM6: 3.161948 | AN6: 3.2532267 | AO6: 3.347002 | AP6: 3.4433434 | AQ6: 3.5423219 | AR6: 3.6440106 | AS6: 3.7484841 | AT6: 3.8558191 | AU6: 3.9660944 | AV6: 4.0793909 | AW6: 4.1957916 | AX6: 4.3153818 | AY6: 4.4382493 | AZ6: 4.5644841 | BA6: 4.6941788 | BB6: 4.8274285 | BC6: 4.9643308 | BD6: 5.1049862 | BE6: 5.2494978 | BF6: 5.3979717 | BG6: 5.5505167 | BH6: 5.7072447 | BI6: 5.8682708 | BJ6: 6.033713 | BK6: 6.2036928 | BL6: 6.3783348 | BM6: 6.5577672 | BN6: 6.7421218 | BO6: 6.9315337 | BP6: 7.1261421 | BQ6: 7.3260897 | BR6: 7.5315234 | BS6: 7.7425939 | BT6: 7.9594562 | BU6: 8.1822695 | BV6: 8.4111974 | BW6: 8.6464081 | BX6: 8.8880742 | BY6: 9.1363731 | BZ6: 9.3914874 | CA6: 9.6536042 | CB6: 9.9229162 | CC6: 10.199621 | CD6: 10.483922 | CE6: 10.776028 | CF6: 11.076154 | CG6: 11.38452 | CH6: 11.701353 | CI6: 12.026885
A7: BAU | B7: c-P_C | C7: a-ATP | D7: 1 | E7: 1.0098086 | F7: 1.018492 | G7: 0.95209688 | H7: 0.99314845 | I7: 1.0281908 | J7: 1.0404815 | K7: 1.0541608 | L7: 1.1535899 | M7: 1.2497978 | N7: 1.3413402 | O7: 1.4295791 | P7: 1.5164381 | Q7: 1.6032639 | R7: 1.6892025 | S7: 1.7767171 | T7: 1.8658485 | U7: 1.9559166 | V7: 2.0465791 | W7: 2.1373216 | X7: 2.229079 | Y7: 2.3218042 | Z7: 2.416089 | AA7: 2.5121156 | AB7: 2.6087908 | AC7: 2.7074122 | AD7: 2.8078932 | AE7: 2.9104369 | AF7: 3.0152592 | AG7: 3.1214468 | AH7: 3.2302606 | AI7: 3.3418201 | AJ7: 3.4563245 | AK7: 3.5742167 | AL7: 3.695934 | AM7: 3.8216035 | AN7: 3.9513556 | AO7: 4.0853244 | AP7: 4.2236476 | AQ7: 4.3664671 | AR7: 4.5139291 | AS7: 4.6661843 | AT7: 4.8233883 | AU7: 4.9857014 | AV7: 5.1532894 | AW7: 5.3263232 | AX7: 5.5049791 | AY7: 5.6894394 | AZ7: 5.8798921 | BA7: 6.0765314 | BB7: 6.2795578 | BC7: 6.489178 | BD7: 6.7056059 | BE7: 6.9290619 | BF7: 7.1597738 | BG7: 7.3979766 | BH7: 7.6439131 | BI7: 7.8978338 | BJ7: 8.1599974 | BK7: 8.430671 | BL7: 8.7101303 | BM7: 8.9986601 | BN7: 9.2965541 | BO7: 9.6041158 | BP7: 9.9216585 | BQ7: 10.249505 | BR7: 10.587991 | BS7: 10.937459 | BT7: 11.298266 | BU7: 11.670779 | BV7: 12.055378 | BW7: 12.452455 | BX7: 12.862412 | BY7: 13.285669 | BZ7: 13.722656 | CA7: 14.173817 | CB7: 14.639613 | CC7: 15.120517 | CD7: 15.617019 | CE7: 16.129625 | CF7: 16.658856 | CG7: 17.205251 | CH7: 17.769367 | CI7: 18.351778
A8: BAU | B8: ener | C8: a-OTP | D8: 1 | E8: 1.0113139 | F8: 1.0214858 | G8: 0.95350973 | H8: 0.99726944 | I8: 1.0349278 | J8: 1.0489416 | K8: 1.0644446 | L8: 1.1698788 | M8: 1.2724913 | N8: 1.3706918 | O8: 1.4658526 | P8: 1.5599719 | Q8: 1.6544629 | R8: 1.7484011 | S8: 1.8444167 | T8: 1.9425611 | U8: 2.0421075 | V8: 2.1426869 | W8: 2.2437392 | X8: 2.3462786 | Y8: 2.450257 | Z8: 2.5563261 | AA8: 2.6646946 | AB8: 2.7741684 | AC8: 2.886181 | AD8: 3.0006484 | AE8: 3.1178067 | AF8: 3.2379088 | AG8: 3.3599507 | AH8: 3.4853482 | AI8: 3.6142524 | AJ8: 3.7469046 | AK8: 3.8838229 | AL8: 4.0255231 | AM8: 4.1721751 | AN8: 4.3239541 | AO8: 4.4810401 | AP8: 4.6436192 | AQ8: 4.8118833 | AR8: 4.9860308 | AS8: 5.1662667 | AT8: 5.3528031 | AU8: 5.5458592 | AV8: 5.7456619 | AW8: 5.952446 | AX8: 6.1664542 | AY8: 6.387938 | AZ8: 6.6171571 | BA8: 6.8543809 | BB8: 7.0998875 | BC8: 7.3539652 | BD8: 7.6169121 | BE8: 7.8890365 | BF8: 8.1706577 | BG8: 8.4621061 | BH8: 8.7637233 | BI8: 9.0758631 | BJ8: 9.3988913 | BK8: 9.7331868 | BL8: 10.079141 | BM8: 10.43716 | BN8: 10.807664 | BO8: 11.191085 | BP8: 11.587875 | BQ8: 11.998496 | BR8: 12.423432 | BS8: 12.863178 | BT8: 13.318252 | BU8: 13.789184 | BV8: 14.276528 | BW8: 14.780854 | BX8: 15.302753 | BY8: 15.842835 | BZ8: 16.401734 | CA8: 16.980102 | CB8: 17.578619 | CC8: 18.197984 | CD8: 18.838923 | CE8: 19.502185 | CF8: 20.188548 | CG8: 20.898814 | CH8: 21.633816 | CI8: 22.394413
A9: BAU | B9: ener | C9: a-WTP | D9: 1 | E9: 1.0093778 | F9: 1.0177536 | G9: 0.95916177 | H9: 0.99667523 | I9: 1.028687 | J9: 1.0403036 | K9: 1.0531595 | L9: 1.1424862 | M9: 1.2282507 | N9: 1.3093217 | O9: 1.3870229 | P9: 1.4631126 | Q9: 1.5388028 | R9: 1.6133892 | S9: 1.689007 | T9: 1.7656935 | U9: 1.8428759 | V9: 1.9202753 | W9: 1.9974725 | X9: 2.0752634 | Y9: 2.1536143 | Z9: 2.233021 | AA9: 2.3136338 | AB9: 2.3945523 | AC9: 2.4768471 | AD9: 2.5604442 | AE9: 2.6455064 | AF9: 2.7322047 | AG9: 2.819795 | AH9: 2.9092954 | AI9: 3.0007944 | AJ9: 3.0944433 | AK9: 3.1905869 | AL9: 3.2895613 | AM9: 3.3914528 | AN9: 3.4963495 | AO9: 3.6043416 | AP9: 3.7155214 | AQ9: 3.8299836 | AR9: 3.9478258 | AS9: 4.0691479 | AT9: 4.194053 | AU9: 4.322647 | AV9: 4.455039 | AW9: 4.591341 | AX9: 4.7316687 | AY9: 4.876141 | AZ9: 5.0248803 | BA9: 5.1780126 | BB9: 5.3356678 | BC9: 5.4979794 | BD9: 5.6650849 | BE9: 5.837126 | BF9: 6.0142486 | BG9: 6.1966026 | BH9: 6.3843426 | BI9: 6.5776278 | BJ9: 6.7766219 | BK9: 6.9814936 | BL9: 7.1924166 | BM9: 7.4095695 | BN9: 7.6331366 | BO9: 7.8633071 | BP9: 8.1002763 | BQ9: 8.344245 | BR9: 8.59542 | BS9: 8.8540142 | BT9: 9.1202467 | BU9: 9.3943434 | BV9: 9.6765364 | BW9: 9.9670652 | BX9: 10.266176 | BY9: 10.574122 | BZ9: 10.891165 | CA9: 11.217573 | CB9: 11.553623 | CC9: 11.8996 | CD9: 12.255797 | CE9: 12.622517 | CF9: 13.00007 | CG9: 13.388776 | CH9: 13.788966 | CI9: 14.200977
A10: BAU | B10: ener | C10: a-ATP | D10: 1 | E10: 1.0108195 | F10: 1.020532 | G10: 0.95495889 | H10: 0.997131 | I10: 1.0333472 | J10: 1.0467463 | K10: 1.0615695 | L10: 1.1628603 | M10: 1.2611024 | N10: 1.3548277 | O10: 1.4453992 | P10: 1.5347542 | Q10: 1.624253 | R10: 1.7130296 | S10: 1.8035823 | T10: 1.8959574 | U10: 1.9894683 | V10: 2.0837699 | W10: 2.1783397 | X10: 2.2741321 | Y10: 2.3711025 | Z10: 2.4698591 | AA10: 2.5705934 | AB10: 2.6721912 | AC10: 2.7759854 | AD10: 2.8818933 | AE10: 2.9901295 | AF10: 3.100923 | AG10: 3.2133408 | AH10: 3.3286866 | AI10: 3.4470924 | AJ10: 3.5687727 | AK10: 3.6941946 | AL10: 3.8238215 | AM10: 3.9577972 | AN10: 4.0962697 | AO10: 4.2393911 | AP10: 4.3873181 | AQ10: 4.5402122 | AR10: 4.6982401 | AS10: 4.8615737 | AT10: 5.0303907 | AU10: 5.2048746 | AV10: 5.3852151 | AW10: 5.5716079 | AX10: 5.7642554 | AY10: 5.9633669 | AZ10: 6.1691584 | BA10: 6.3818534 | BB10: 6.6016827 | BC10: 6.8288849 | BD10: 7.0637064 | BE10: 7.306402 | BF10: 7.5572351 | BG10: 7.8164778 | BH10: 8.0844113 | BI10: 8.3613261 | BJ10: 8.6475225 | BK10: 8.943311 | BL10: 9.2490124 | BM10: 9.5649579 | BN10: 9.8914903 | BO10: 10.228964 | BP10: 10.577743 | BQ10: 10.938208 | BR10: 11.310748 | BS10: 11.695768 | BT10: 12.093684 | BU10: 12.504927 | BV10: 12.929945 | BW10: 13.369196 | BX10: 13.823158 | BY10: 14.292322 | BZ10: 14.777196 | CA10: 15.278306 | CB10: 15.796195 | CC10: 16.331424 | CD10: 16.884572 | CE10: 17.45624 | CF10: 18.047046 | CG10: 18.65763 | CH10: 19.288654 | CI10: 19.940802
A11: BAU | B11: ener | C11: a-otpEle | D11: 1 | E11: 1.0084725 | F11: 1.0160108 | G11: 0.96178379 | H11: 0.99634955 | I11: 1.025722 | J11: 1.0362268 | K11: 1.0478589 | L11: 1.1297624 | M11: 1.2078925 | N11: 1.281313 | O11: 1.3513124 | P11: 1.4195356 | Q11: 1.4871039 | R11: 1.5534073 | S11: 1.6203687 | T11: 1.6880228 | U11: 1.7558645 | V11: 1.8236543 | W11: 1.8910321 | X11: 1.9587043 | Y11: 2.026645 | Z11: 2.0952887 | AA11: 2.164765 | AB11: 2.2342937 | AC11: 2.3048026 | AD11: 2.3762249 | AE11: 2.4486975 | AF11: 2.5223631 | AG11: 2.5965824 | AH11: 2.6722218 | AI11: 2.74935 | AJ11: 2.8280884 | AK11: 2.9087205 | AL11: 2.9915198 | AM11: 3.0765474 | AN11: 3.1638654 | AO11: 3.253537 | AP11: 3.3456268 | AQ11: 3.440201 | AR11: 3.5373271 | AS11: 3.6370747 | AT11: 3.739515 | AU11: 3.844721 | AV11: 3.9527677 | AW11: 4.0637323 | AX11: 4.1776938 | AY11: 4.2947334 | AZ11: 4.4149346 | BA11: 4.5383831 | BB11: 4.665167 | BC11: 4.7953766 | BD11: 4.9291048 | BE11: 5.066447 | BF11: 5.2075011 | BG11: 5.3523679 | BH11: 5.5011505 | BI11: 5.6539553 | BJ11: 5.8108911 | BK11: 5.97207 | BL11: 6.137607 | BM11: 6.3076202 | BN11: 6.482231 | BO11: 6.661564 | BP11: 6.8457472 | BQ11: 7.0349121 | BR11: 7.2291937 | BS11: 7.4287308 | BT11: 7.6336658 | BU11: 7.844145 | BV11: 8.0603188 | BW11: 8.2823414 | BX11: 8.5103716 | BY11: 8.7445721 | BZ11: 8.9851102 | CA11: 9.2321577 | CB11: 9.4858912 | CC11: 9.7464918 | CD11: 10.014146 | CE11: 10.289044 | CF11: 10.571384 | CG11: 10.861366 | CH11: 11.159198 | CI11: 11.465093
A12: BAU | B12: gas_gdt | C12: a-OTP | D12: 8.7489846 | E12: 8.8479697 | F12: 8.9369634 | G12: 8.3422419 | H12: 8.7250949 | I12: 9.0545677 | J12: 9.1771741 | K12: 9.3128096 | L12: 10.235252 | M12: 11.133007 | N12: 11.992161 | O12: 12.824721 | P12: 13.64817 | Q12: 14.474871 | R12: 15.296735 | S12: 16.136773 | T12: 16.995437 | U12: 17.866367 | V12: 18.746334 | W12: 19.63044 | X12: 20.527555 | Y12: 21.437261 | Z12: 22.365258 | AA12: 23.313372 | AB12: 24.271156 | AC12: 25.251153 | AD12: 26.252626 | AE12: 27.277643 | AF12: 28.328414 | AG12: 29.396157 | AH12: 30.493258 | AI12: 31.621038 | AJ12: 32.781611 | AK12: 33.979507 | AL12: 35.219239 | AM12: 36.502296 | AN12: 37.830207 | AO12: 39.204551 | AP12: 40.626953 | AQ12: 42.099093 | AR12: 43.622707 | AS12: 45.199588 | AT12: 46.831592 | AU12: 48.520636 | AV12: 50.268707 | AW12: 52.077858 | AX12: 53.950213 | AY12: 55.88797 | AZ12: 57.893406 | BA12: 59.968872 | BB12: 62.116806 | BC12: 64.339728 | BD12: 66.640246 | BE12: 69.021059 | BF12: 71.484958 | BG12: 74.034835 | BH12: 76.67368 | BI12: 79.404586 | BJ12: 82.230755 | BK12: 85.155501 | BL12: 88.182252 | BM12: 91.314556 | BN12: 94.556083 | BO12: 97.910633 | BP12: 101.38214 | BQ12: 104.97466 | BR12: 108.69241 | BS12: 112.53975 | BT12: 116.52118 | BU12: 120.64136 | BV12: 124.90513 | BW12: 129.31747 | BX12: 133.88355 | BY12: 138.60872 | BZ12: 143.49851 | CA12: 148.55865 | CB12: 153.79507 | CC12: 159.21388 | CD12: 164.82144 | CE12: 170.62432 | CF12: 176.62929 | CG12: 182.8434 | CH12: 189.27392 | CI12: 195.92837
A13: BAU | B13: gas_gdt | C13: a-WTP | D13: 46.660772 | E13: 47.098347 | F13: 47.489169 | G13: 44.755229 | H13: 46.505636 | I13: 47.999332 | J13: 48.541369 | K13: 49.141234 | L13: 53.309288 | M13: 57.311124 | N13: 61.093962 | O13: 64.719557 | P13: 68.269966 | Q13: 71.801728 | R13: 75.281985 | S13: 78.810371 | T13: 82.388623 | U13: 85.990012 | V13: 89.601529 | W13: 93.203611 | X13: 96.833392 | Y13: 100.48931 | Z13: 104.19449 | AA13: 107.95594 | AB13: 111.73166 | AC13: 115.5716 | AD13: 119.4723 | AE13: 123.44137 | AF13: 127.48678 | AG13: 131.57381 | AH13: 135.74997 | AI13: 140.01938 | AJ13: 144.38912 | AK13: 148.87525 | AL13: 153.49347 | AM13: 158.24781 | AN13: 163.14237 | AO13: 168.18136 | AP13: 173.3691 | AQ13: 178.70999 | AR13: 184.2086 | AS13: 189.86958 | AT13: 195.69775 | AU13: 201.69805 | AV13: 207.87556 | AW13: 214.23552 | AX13: 220.78332 | AY13: 227.5245 | AZ13: 234.46479 | BA13: 241.61007 | BB13: 248.96638 | BC13: 256.53996 | BD13: 264.33724 | BE13: 272.36481 | BF13: 280.62948 | BG13: 289.13826 | BH13: 297.89835 | BI13: 306.91719 | BJ13: 316.20241 | BK13: 325.76188 | BL13: 335.60371 | BM13: 345.73624 | BN13: 356.16805 | BO13: 366.90798 | BP13: 377.96515 | BQ13: 389.34892 | BR13: 401.06893 | BS13: 413.13514 | BT13: 425.55775 | BU13: 438.34732 | BV13: 451.51466 | BW13: 465.07096 | BX13: 479.02769 | BY13: 493.39669 | BZ13: 508.19015 | CA13: 523.4206 | CB13: 539.10096 | CC13: 555.24452 | CD13: 571.86497 | CE13: 588.97639 | CF13: 606.59331 | CG13: 624.73064 | CH13: 643.40378 | CI13: 662.62856
... A98: BAU | B98: nrgFac | C98: a-macc | D98: 1 | E98: 1.005 | F98: 1.010025 | G98: 1.0150751 | H98: 1.0201505 | I98: 1.0252513 | J98: 1.0303775 | K98: 1.0355294 | L98: 1.040707 | M98: 1.0459106 | N98: 1.0511401 | O98: 1.0563958 | P98: 1.0616778 | Q98: 1.0669862 | R98: 1.0723211 | S98: 1.0776827 | T98: 1.0830712 | U98: 1.0884865 | V98: 1.0939289 | W98: 1.0993986 | X98: 1.1048956 | Y98: 1.1104201 | Z98: 1.1159722 | AA98: 1.121552 | AB98: 1.1271598 | AC98: 1.1327956 | AD98: 1.1384596 | AE98: 1.1441519 | AF98: 1.1498726 | AG98: 1.155622 | AH98: 1.1614001 | AI98: 1.1672071 | AJ98: 1.1730431 | AK98: 1.1789083 | AL98: 1.1848029 | AM98: 1.1907269 | AN98: 1.1966805 | AO98: 1.2026639 | AP98: 1.2086772 | AQ98: 1.2147206 | AR98: 1.2207942 | AS98: 1.2268982 | AT98: 1.2330327 | AU98: 1.2391979 | AV98: 1.2453939 | AW98: 1.2516208 | AX98: 1.2578789 | AY98: 1.2641683 | AZ98: 1.2704892 | BA98: 1.2768416 | BB98: 1.2832258 | BC98: 1.2896419 | BD98: 1.2960902 | BE98: 1.3025706 | BF98: 1.3090835 | BG98: 1.3156289 | BH98: 1.322207 | BI98: 1.3288181 | BJ98: 1.3354621 | BK98: 1.3421395 | BL98: 1.3488502 | BM98: 1.3555944 | BN98: 1.3623724 | BO98: 1.3691842 | BP98: 1.3760302 | BQ98: 1.3829103 | BR98: 1.3898249 | BS98: 1.396774 | BT98: 1.4037579 | BU98: 1.4107766 | BV98: 1.4178305 | BW98: 1.4249197 | BX98: 1.4320443 | BY98: 1.4392045 | BZ98: 1.4464005 | CA98: 1.4536325 | CB98: 1.4609007 | CC98: 1.4682052 | CD98: 1.4755462 | CE98: 1.4829239 | CF98: 1.4903386 | CG98: 1.4977903 | CH98: 1.5052792 | CI98: 1.5128056
A99: BAU | B99: pwm | C99: c-COA | D99: 67.8 | E99: 67.8 | F99: 67.8 | G99: 67.8 | H99: 147.9 | I99: 344.9 | J99: 231.7 | K99: 200.8 | L99: 181.6 | M99: 162.5 | N99: 143.3 | O99: 124.2 | P99: 105 | Q99: 85.9 | R99: 84.6 | S99: 83.4 | T99: 82.2 | U99: 81 | V99: 79.8 | W99: 79.4 | X99: 79.1 | Y99: 78.8 | Z99: 78.4 | AA99: 78.1 | AB99: 77.6 | AC99: 77.1 | AD99: 76.6 | AE99: 76.1 | AF99: 75.6 | AG99: 75.5 | AH99: 75.4 | AI99: 75.3 | AJ99: 75.2 | AK99: 75.1
A100: BAU | B100: pwm | C100: c-OIL | D100: 47.2 | E100: 47.2 | F100: 47.2 | G100: 47.2 | H100: 75.5 | I100: 99.8 | J100: 88.8 | K100: 75.7 | L100: 77.7 | M100: 79.7 | N100: 81.7 | O100: 83.8 | P100: 85.8 | Q100: 87.8 | R100: 88.3 | S100: 88.7 | T100: 89.1 | U100: 89.5 | V100: 90 | W100: 90.8 | X100: 91.7 | Y100: 92.5 | Z100: 93.4 | AA100: 94.3 | AB100: 94.8 | AC100: 95.3 | AD100: 95.9 | AE100: 96.4 | AF100: 96.9 | AG100: 97.9 | AH100: 98.9 | AI100: 99.8 | AJ100: 100.8 | AK100: 101.8
A101: BAU | B101: pwm | C101: c-GAS | D101: 2.2 | E101: 2.2 | F101: 2.2 | G101: 2.2 | H101: 4.1 | I101: 6.4 | J101: 6 | K101: 5.7 | L101: 5.4 | M101: 5.2 | N101: 5 | O101: 4.7 | P101: 4.5 | Q101: 4.3 | R101: 4.3 | S101: 4.3 | T101: 4.3 | U101: 4.4 | V101: 4.4 | W101: 4.4 | X101: 4.4 | Y101: 4.5 | Z101: 4.5 | AA101: 4.5 | AB101: 4.5 | AC101: 4.5 | AD101: 4.6 | AE101: 4.6 | AF101: 4.6 | AG101: 4.7 | AH101: 4.8 | AI101: 4.9 | AJ101: 4.9 | AK101: 5
A102: BAU | B102: pwm | C102: c-P_C | D102: 47.2 | E102: 47.2 | F102: 47.2 | G102: 47.2 | H102: 75.5 | I102: 99.8 | J102: 88.8 | K102: 75.7 | L102: 77.7 | M102: 79.7 | N102: 81.7 | O102: 83.8 | P102: 85.8 | Q102: 87.8 | R102: 88.3 | S102: 88.7 | T102: 89.1 | U102: 89.5 | V102: 90 | W102: 90.8 | X102: 91.7 | Y102: 92.5 | Z102: 93.4 | AA102: 94.3 | AB102: 94.8 | AC102: 95.3 | AD102: 95.9 | AE102: 96.4 | AF102: 96.9 | AG102: 97.9 | AH102: 98.9 | AI102: 99.8 | AJ102: 100.8 | AK102: 101.8
A103: NZ | B103: pwm | C103: c-COA | D103: 67.8 | E103: 67.8 | F103: 67.8 | G103: 67.8 | H103: 147.9 | I103: 344.9 | J103: 231.7 | K103: 200.8 | L103: 177.4 | M103: 154 | N103: 130.5 | O103: 107.1 | P103: 83.7 | Q103: 60.3 | R103: 59.7 | S103: 59.2 | T103: 58.6 | U103: 58 | V103: 57.4 | W103: 56.8 | X103: 56.2 | Y103: 55.6 | Z103: 55 | AA103: 54.4 | AB103: 53.9 | AC103: 53.3 | AD103: 52.7 | AE103: 52.1 | AF103: 51.5 | AG103: 50.9 | AH103: 50.3 | AI103: 49.7 | AJ103: 49.1 | AK103: 48.6
A104: NZ | B104: pwm | C104: c-OIL | D104: 47.2 | E104: 47.2 | F104: 47.2 | G104: 47.2 | H104: 75.5 | I104: 99.8 | J104: 88.8 | K104: 75.7 | L104: 68.9 | M104: 62.1 | N104: 55.3 | O104: 48.6 | P104: 41.8 | Q104: 35 | R104: 34.5 | S104: 33.9 | T104: 33.4 | U104: 32.8 | V104: 32.3 | W104: 31.7 | X104: 31.2 | Y104: 30.6 | Z104: 30.1 | AA104: 29.5 | AB104: 29 | AC104: 28.4 | AD104: 27.9 | AE104: 27.3 | AF104: 26.8 | AG104: 26.2 | AH104: 25.7 | AI104: 25.1 | AJ104: 24.6 | AK104: 24
A105: NZ | B105: pwm | C105: c-GAS | D105: 2.2 | E105: 2.2 | F105: 2.2 | G105: 2.2 | H105: 4.1 | I105: 6.4 | J105: 6 | K105: 5.7 | L105: 5.4 | M105: 5.1 | N105: 4.8 | O105: 4.5 | P105: 4.2 | Q105: 4 | R105: 3.9 | S105: 3.8 | T105: 3.7 | U105: 3.6 | V105: 3.5 | W105: 3.4 | X105: 3.3 | Y105: 3.2 | Z105: 3.1 | AA105: 3 | AB105: 3 | AC105: 2.9 | AD105: 2.9 | AE105: 2.8 | AF105: 2.8 | AG105: 2.8 | AH105: 2.8 | AI105: 2.8 | AJ105: 2.8 | AK105: 2.8
A106: NZ | B106: pwm | C106: c-P_C | D106: 47.2 | E106: 47.2 | F106: 47.2 | G106: 47.2 | H106: 75.5 | I106: 99.8 | J106: 88.8 | K106: 75.7 | L106: 68.9 | M106: 62.1 | N106: 55.3 | O106: 48.6 | P106: 41.8 | Q106: 35 | R106: 34.5 | S106: 33.9 | T106: 33.4 | U106: 32.8 | V106: 32.3 | W106: 31.7 | X106: 31.2 | Y106: 30.6 | Z106: 30.1 | AA106: 29.5 | AB106: 29 | AC106: 28.4 | AD106: 27.9 | AE106: 27.3 | AF106: 26.8 | AG106: 26.2 | AH106: 25.7 | AI106: 25.1 | AJ106: 24.6 | AK106: 24

Sheet Nutrients
B1: cal | C1: prot | D1: fat
A2: c-PDR | B2: 3050.6236 | C2: 59.096226 | D2: 8.4521864
A3: c-WHT | B3: 54811.847 | C3: 1654.6856 | D3: 260.61364
A4: c-GRO | B4: 29196.871 | C4: 780.10824 | D4: 221.48257
A5: c-V_F | B5: 7161.5305 | C5: 182.21397 | D5: 57.815429
A6: c-OSD | B6: 1735.7034 | C6: 49.446609 | D6: 94.509177
A7: c-C_B | B7: 804.46793 | C7: 23.555476 | D7: 10.394504
A8: c-PFB | B8: 2050.034 | C8: 60.266536 | D8: 26.18183
A9: c-OCR | B9: 1636.5854 | C9: 67.91458 | D9: 49.609797
A10: c-CTL | B10: 112.53815 | C10: 3.6015898 | D10: 4.5186149
A11: c-OAP | B11: 854.56976 | C11: 63.657427 | D11: 55.29293
A12: c-RMK | B12: 14182.892 | C12: 948.5258 | D12: 770.0032
A13: c-WOL | B13: 179.66246 | C13: 5.7707742 | D13: 5.9869458
... A27: sum | B27: 3395 | C27: 92.39 | D27: 101.67

Sheet SAM
B1: a-PDR_0 | C1: a-WHT_0 | D1: a-GRO_0 | E1: a-V_F_0 | F1: a-OSD_0 | G1: a-C_B_0 | H1: a-PFB_0 | I1: a-OCR_0 | J1: a-CTL_0 | K1: a-OAP_0 | L1: a-RMK_0 | M1: a-WOL_0 | N1: a-FRS_0 | O1: a-FSH_0 | P1: a-COA_0 | Q1: a-OIL_0 | R1: a-GAS_0 | S1: a-OXT_0 | T1: a-CMT_0 | U1: a-OMT_0 | V1: a-VOL_0 | W1: a-MIL_0 | X1: a-PCR_0 | Y1: a-SGR_0 | Z1: a-OFD_0 | AA1: a-B_T_0 | AB1: a-TEX_0 | AC1: a-WAP_0 | AD1: a-LEA_0 | AE1: a-LUM_0 | AF1: a-PPP_0 | AG1: a-P_C_0 | AH1: a-CHM_0 | AI1: a-BPH_0 | AJ1: a-RPP_0 | AK1: a-NMM_0 | AL1: a-I_S_0 | AM1: a-NFM_0 | AN1: a-FMP_0 | AO1: a-ELE_0 | AP1: a-EEQ_0 | AQ1: a-OME_0 | AR1: a-MVH_0 | AS1: a-OTN_0 | AT1: a-OMF_0 | AU1: a-TnD_0 | AV1: a-NuclearBL_0 | AW1: a-CoalBL_0 | AX1: a-GasBL_0 | AY1: a-WindBL_0 | AZ1: a-HydroBL_0 | BA1: a-OilBL_0 | BB1: a-OtherBL_0 | BC1: a-GasP_0 | BD1: a-HydroP_0 | BE1: a-OilP_0 | BF1: a-SolarP_0 | BG1: a-GDT_0 | BH1: a-WTR_0 | BI1: a-CNS_0 | BJ1: a-TRD_0 | BK1: a-AFS_0 | BL1: a-OTP_0 | BM1: a-WTP_0 | BN1: a-ATP_0 | BO1: a-WHS_0 | BP1: a-CMN_0 | BQ1: a-OFI_0 | BR1: a-INS_0 | BS1: a-RSA_0 | BT1: a-OBS_0 | BU1: a-ROS_0 | BV1: a-OSG_0 | BW1: a-EDU_0 | BX1: a-HHT_0 | BY1: a-DWE_0 | BZ1: a-ctlRais_0 | CA1: a-otpEle_0 | CB1: a-macc_0 | CC1: c-PDR_0 | CD1: c-WHT_0 | CE1: c-GRO_0 | CF1: c-V_F_0 | CG1: c-OSD_0 | CH1: c-C_B_0 | CI1: c-PFB_0 | CJ1: c-OCR_0 | CK1: c-CTL_0 | CL1: c-OAP_0 | CM1: c-RMK_0 | CN1: c-WOL_0 | CO1: c-FRS_0 | CP1: c-FSH_0 | CQ1: c-COA_0 | CR1: c-OIL_0 | CS1: c-GAS_0 | CT1: c-OXT_0 | CU1: c-CMT_0 | CV1: c-OMT_0 | CW1: c-VOL_0 | CX1: c-MIL_0 | CY1: c-PCR_0 | CZ1: c-SGR_0 | DA1: c-OFD_0 | DB1: c-B_T_0 | DC1: c-TEX_0 | DD1: c-WAP_0 | DE1: c-LEA_0 | DF1: c-LUM_0 | DG1: c-PPP_0 | DH1: c-P_C_0 | DI1: c-CHM_0 | DJ1: c-BPH_0 | DK1: c-RPP_0 | DL1: c-NMM_0 | DM1: c-I_S_0 | DN1: c-NFM_0 | DO1: c-FMP_0 | DP1: c-ELE_0 | DQ1: c-EEQ_0 | DR1: c-OME_0 | DS1: c-MVH_0 | DT1: c-OTN_0 | DU1: c-OMF_0 | DV1: c-TnD_0 | DW1: c-NuclearBL_0 | DX1: c-CoalBL_0 | DY1: c-GasBL_0 | DZ1: c-WindBL_0 | EA1: c-HydroBL_0 | EB1: c-OilBL_0 | EC1: c-OtherBL_0 | ED1: c-GasP_0 | EE1: c-HydroP_0 | EF1: c-OilP_0 | EG1: c-SolarP_0 | EH1: c-GDT_0 | EI1: c-WTR_0 | EJ1: c-CNS_0 | EK1: c-TRD_0 | EL1: c-AFS_0 | EM1: c-OTP_0 | EN1: c-WTP_0 | EO1: c-ATP_0 | EP1: c-WHS_0 | EQ1: c-CMN_0 | ER1: c-OFI_0 | ES1: c-INS_0 | ET1: c-RSA_0 | EU1: c-OBS_0 | EV1: c-ROS_0 | EW1: c-OSG_0 | EX1: c-EDU_0 | EY1: c-HHT_0 | EZ1: c-DWE_0 | FA1: c-ctlRais_0 | FB1: c-otpEle_0 | FC1: c-macc_0 | FD1: f-tech_aspros_0 | FE1: f-clerks_0 | FF1: f-service_shop_0 | FG1: f-off_mgr_pros_0 | FH1: f-ag_othlowsk_0 | FI1: f-Capital_0 | FJ1: f-Land_0 | FK1: f-NatlRes_0 | FL1: f-AEZ1_0 | FM1: f-AEZ2_0 | FN1: f-AEZ3_0 | FO1: f-AEZ4_0 | FP1: f-AEZ5_0 | FQ1: f-AEZ6_0 | FR1: f-AEZ7_0 | FS1: f-AEZ8_0 | FT1: f-AEZ9_0 | FU1: f-AEZ10_0 | FV1: f-AEZ11_0 | FW1: f-AEZ12_0 | FX1: f-AEZ13_0 | FY1: f-AEZ14_0 | FZ1: f-AEZ15_0 | GA1: f-AEZ16_0 | GB1: f-AEZ17_0 | GC1: f-AEZ18_0 | GD1: f-water_0 | GE1: f-m_skl_0 | GF1: f-f_skl_0 | GG1: f-m_nsk_0 | GH1: f-f_nsk_0 | GI1: f-m_tech_aspros_0 | GJ1: f-f_tech_aspros_0 | GK1: f-m_clerks_0 | GL1: f-f_clerks_0 | GM1: f-m_service_shop_0 | GN1: f-f_service_shop_0 | GO1: f-m_off_mgr_pros_0 | GP1: f-f_off_mgr_pros_0 | GQ1: f-m_ag_othlowsk_0 | GR1: f-f_ag_othlowsk_0 | GS1: t-tech_aspros_0 | GT1: t-clerks_0 | GU1: t-service_shop_0 | GV1: t-off_mgr_pros_0 | GW1: t-ag_othlowsk_0 | GX1: t-Capital_0 | GY1: t-Land_0 | GZ1: t-NatlRes_0 | HA1: t-AEZ1_0 | HB1: t-AEZ2_0 | HC1: t-AEZ3_0 | HD1: t-AEZ4_0 | HE1: t-AEZ5_0 | HF1: t-AEZ6_0 | HG1: t-AEZ7_0 | HH1: t-AEZ8_0 | HI1: t-AEZ9_0 | HJ1: t-AEZ10_0 | HK1: t-AEZ11_0 | HL1: t-AEZ12_0 | HM1: t-AEZ13_0 | HN1: t-AEZ14_0 | HO1: t-AEZ15_0 | HP1: t-AEZ16_0 | HQ1: t-AEZ17_0 | HR1: t-AEZ18_0 | HS1: t-water_0 | HT1: t-m_skl_0 | HU1: t-f_skl_0 | HV1: t-m_nsk_0 | HW1: t-f_nsk_0 | HX1: t-m_tech_aspros_0 | HY1: t-f_tech_aspros_0 | HZ1: t-m_clerks_0 | IA1: t-f_clerks_0 | IB1: t-m_service_shop_0 | IC1: t-f_service_shop_0 | ID1: t-m_off_mgr_pros_0 | IE1: t-f_off_mgr_pros_0 | IF1: t-m_ag_othlowsk_0 | IG1: t-f_ag_othlowsk_0 | IH1: t-stx_0 | II1: t-prodtax_0 | IJ1: t-dirtax_0 | IK1: t-imp_0 | IL1: t-exp_0 | IM1: h-hhold_0 | IN1: g-govt_0 | IO1: e-ent_0 | IP1: i-cgds_0 | IQ1: i-ginv_0 | IR1: debt_0 | IS1: w-ww_world_0
A2: a-PDR_0 | CC2: 5.4834795
A3: a-WHT_0 | CD3: 653.83405
A4: a-GRO_0 | CE4: 193.01873
A5: a-V_F_0 | CF5: 11175.347
A6: a-OSD_0 | CG6: 101.08824
A7: a-C_B_0 | G7: 1e-20
A8: a-PFB_0 | H8: 1e-20
A9: a-OCR_0 | CJ9: 13.148828
A10: a-CTL_0 | CK10: 3819.6001
A11: a-OAP_0 | CL11: 1054.7532
A12: a-RMK_0 | CM12: 744.83319
A13: a-WOL_0 | CN13: 116.02174
A14: a-FRS_0 | CO14: 725.0202
A15: a-FSH_0 | CP15: 19.937112
A16: a-COA_0 | CQ16: 11.185048
A17: a-OIL_0 | CR17: 18462.773
A18: a-GAS_0 | CS18: 39953.685
A19: a-OXT_0 | CT19: 757.09295
A20: a-CMT_0 | CU20: 628.24343
A21: a-OMT_0 | CV21: 291.14405
A22: a-VOL_0 | CW22: 222.70168
A23: a-MIL_0 | CX23: 912.35912
A24: a-PCR_0 | CY24: 3.8267573
A25: a-SGR_0 | CZ25: 262.97839
A26: a-OFD_0 | DA26: 3926.6595
A27: a-B_T_0 | DB27: 2020.657
A28: a-TEX_0 | DC28: 54.766513
A29: a-WAP_0 | DD29: 809.49468
A30: a-LEA_0 | DE30: 1128.2517
A31: a-LUM_0 | DF31: 892.19999
A32: a-PPP_0 | DG32: 814.91556
A33: a-P_C_0 | DH33: 18068.778
A34: a-CHM_0 | DI34: 1599.1209
A35: a-BPH_0 | DJ35: 161.61233
A36: a-RPP_0 | DK36: 987.41524
A37: a-NMM_0 | DL37: 8281.4174
A38: a-I_S_0 | DM38: 738.31674
A39: a-NFM_0 | DN39: 1786.1078
A40: a-FMP_0 | DO40: 6984.6913
A41: a-ELE_0 | DP41: 161.53802
A42: a-EEQ_0 | DQ42: 130.85516
A43: a-OME_0 | DR43: 223.14056
A44: a-MVH_0 | DS44: 265.11358
A45: a-OTN_0 | DT45: 85.48649
A46: a-OMF_0 | DU46: 133.59658
A47: a-TnD_0 | DV47: 704.60864
A48: a-NuclearBL_0 | AV48: 1e-20
A49: a-CoalBL_0 | AW49: 1e-20
A50: a-GasBL_0 | DY50: 4635.302
A51: a-WindBL_0 | AY51: 1e-20
A52: a-HydroBL_0 | AZ52: 1e-20
A53: a-OilBL_0 | BA53: 1e-20
A54: a-OtherBL_0 | BB54: 1e-20
A55: a-GasP_0 | ED55: 1828.0384
A56: a-HydroP_0 | BD56: 1e-20
A57: a-OilP_0 | EF57: 197.69985
A58: a-SolarP_0 | EG58: 20.099262
A59: a-GDT_0 | EH59: 7428.2148
A60: a-WTR_0 | EI60: 1630.6882
A61: a-CNS_0 | EJ61: 40616.386
A62: a-TRD_0 | EK62: 20596.37
A63: a-AFS_0 | EL63: 2611.0863
A64: a-OTP_0 | EM64: 7559.9988
A65: a-WTP_0 | EN65: 769.04897
A66: a-ATP_0 | EO66: 1215.2856
A67: a-WHS_0 | EP67: 2190.5091
A68: a-CMN_0 | EQ68: 10040.237
A69: a-OFI_0 | ER69: 1185.9305
A70: a-INS_0 | ES70: 72.670321
A71: a-RSA_0 | ET71: 288.11546
A72: a-OBS_0 | EU72: 1612.5332
A73: a-ROS_0 | EV73: 832.31672
A74: a-OSG_0 | EW74: 10931.741
A75: a-EDU_0 | EX75: 4752.3957
A76: a-HHT_0 | EY76: 10841.219
A77: a-DWE_0 | EZ77: 870.60815
A78: a-ctlRais_0 | BZ78: 1e-20
A79: a-otpEle_0 | CA79: 1e-20
A80: a-macc_0 | FC80: 0.013154098
A81: c-PDR_0 | B81: 0.0036636302 | D81: 0.01799386 | I81: 0.00061500227 | J81: 0.30383657 | N81: 0.046839246 | O81: 0.0014200943 | W81: 0.086789907 | X81: 0.06586873 | Y81: 0.06962293 | AE81: 0.091008273 | BJ81: 0.5712162 | BK81: 0.45249714 | BP81: 1.5556346 | BU81: 0.018784573 | BV81: 0.70970169 | IS81: 5.8334819e-06
A82: c-WHT_0 | C82: 18.838801 | I82: 0.00039135939 | J82: 12.16243 | K82: 2.0976976 | L82: 2.3441923 | M82: 0.52905391 | N82: 0.31692776 | O82: 0.01114907 | Q82: 0.89170551 | R82: 1.7679559 | S82: 0.2755781 | U82: 0.068475291 | V82: 0.033815891 | W82: 0.38764397 | X82: 0.0029302021 | Y82: 5.6179465 | Z82: 181.15832 | AA82: 313.05602 | AE82: 0.50981997 | AF82: 0.31120388 | AH82: 0.18639839 | AI82: 0.014050673 | AJ82: 0.094801135 | AT82: 0.015013931 | BJ82: 4.5997453 | BK82: 2.9524977 | BL82: 4.0288339 | BM82: 0.47110596 | BN82: 0.4911444 | BO82: 1.1138107 | BP82: 7.6264358 | BQ82: 0.077602606 | BR82: 0.0066213827 | BS82: 0.014650376 | BT82: 0.29267143 | BV82: 0.62009324 | BX82: 0.24931016 | IM82: 1859.7943 | IN82: 25.249654 | IP82: 116.47644 | IS82: 0.015540151
A83: c-GRO_0 | B83: 0.0004731376 | D83: 0.14561278 | J83: 28.572935 | K83: 4.8068023 | L83: 5.4555037 | M83: 1.2306343 | N83: 1.5766745 | O83: 0.056082701 | P83: 0.0010322483 | Q83: 4.1857887 | R83: 10.902591 | S83: 1.3857843 | T83: 0.53233402 | U83: 0.64454441 | V83: 0.28846413 | W83: 3.3287473 | X83: 0.026732625 | Y83: 53.123644 | Z83: 16.615053 | AA83: 7.9237021 | AE83: 2.4914096 | AF83: 1.6306344 | AH83: 0.93581827 | AI83: 0.072231277 | AJ83: 0.47028372 | AL83: 0.24535554 | AM83: 0.65596577 | AN83: 2.2235676 | AT83: 0.072061441 | BI83: 4.4934272 | BJ83: 23.107245 | BK83: 14.364809 | BL83: 20.604828 | BM83: 2.4162945 | BN83: 2.5187391 | BO83: 5.6696926 | BP83: 37.551453 | BQ83: 0.72924658 | BR83: 0.055232944 | BS83: 0.14877081 | BT83: 1.3070382 | BU83: 0.023158128 | BV83: 1.139031 | BX83: 1.6011225 | BY83: 0.001728153 | IM83: 905.13133 | IN83: 12.242265 | IP83: 56.622136 | IS83: 0.0045375969
A84: c-V_F_0 | B84: 0.00030028329 | E84: 41.578364 | I84: 0.00049875731 | J84: 56.770811 | K84: 13.814906 | L84: 10.99851 | M84: 2.4998272 | N84: 9.5614743 | O84: 0.33600798 | P84: 0.0070879116 | Q84: 31.167007 | R84: 52.324814 | S84: 8.3067114 | T84: 1.2524735 | U84: 1.5160184 | V84: 0.78875989 | W84: 8.604121 | X84: 0.059031756 | Y84: 119.38321 | Z84: 780.21863 | AA84: 156.65979 | AD84: 0.079635281 | AE84: 15.938909 | AF84: 8.8705029 | AH84: 4.4646527 | AI84: 3.9904027 | AJ84: 0.62577835 | AK84: 0.85982153 | AL84: 0.72426197 | AM84: 1.9370415 | AN84: 16.62833 | AO84: 0.030555936 | AP84: 0.025549771 | AQ84: 0.042687355 | AR84: 0.062225926 | AS84: 0.021373795 | AT84: 0.41569852 | BI84: 27.152699 | BJ84: 138.53361 | BK84: 89.299133 | BL84: 83.401051 | BM84: 10.033344 | BN84: 10.212237 | BO84: 202.3424 | BP84: 154.25235 | BQ84: 4.6144111 | BR84: 0.5914768 | BS84: 0.46227662 | BT84: 7.6314828 | BU84: 0.28404614 | BV84: 7.3371897 | BW84: 0.10527343 | BX84: 14.100771 | BY84: 0.0029522328 | IM84: 8948.0382 | IN84: 122.44063 | IP84: 560.41078 | IS84: 95.001491
A85: c-OSD_0 | E85: 1.0211477 | F85: 1.7191918 | I85: 0.0013125594 | J85: 0.16399927 | K85: 0.068136461 | L85: 0.037185319 | M85: 0.010446271 | N85: 0.48102242 | O85: 0.016660304 | Q85: 0.8858294 | R85: 4.3319416 | S85: 0.41114596 | T85: 0.080911862 | U85: 0.094973914 | V85: 133.39366 | W85: 0.68440666 | X85: 0.0036539125 | Y85: 7.5376386 | Z85: 14.376875 | AA85: 0.66302149 | AE85: 1.0156473 | AF85: 0.23992608 | AH85: 0.43362844 | AN85: 0.85120487 | AT85: 0.017220975 | BJ85: 6.923588 | BK85: 4.66116 | BL85: 3.7857132 | BM85: 0.45433745 | BN85: 0.43314135 | BO85: 1.0858705 | BP85: 16.553836 | BR85: 0.0011724938 | BT85: 0.49178319 | BV85: 1.1522598 | BX85: 0.25615749 | IS85: 0.060521078
A86: c-C_B_0 | Y86: 0.0032241128
A87: c-PFB_0 | N87: 0.023048192 | O87: 0.00079798007 | X87: 0.00035893745 | Y87: 0.72314057 | AB87: 0.0082716928 | BK87: 0.20659447 | BP87: 0.53360521 | IM87: 8.0419971
A88: c-OCR_0 | E88: 0.2466495 | I88: 0.0063853895 | J88: 0.67332862 | K88: 0.18276874 | L88: 0.25559807 | M88: 0.019117344 | N88: 1.3461899 | O88: 0.047845734 | P88: 0.0010202031 | Q88: 4.0676218 | R88: 7.834171 | S88: 1.1841825 | T88: 0.43748059 | U88: 0.52284152 | V88: 0.27112056 | W88: 2.7196033 | X88: 0.0215016 | Y88: 44.198537 | Z88: 35.04609 | AA88: 38.957716 | AE88: 0.56467513 | AF88: 2.8045435 | AI88: 0.032272865 | AJ88: 1.3272813 | AM88: 2.891762 | AT88: 0.067504267 | BI88: 4.0385549 | BJ88: 19.772583 | BK88: 12.323234 | BL88: 15.715665 | BM88: 1.8481909 | BN88: 1.9160245 | BO88: 4.9869406 | BP88: 35.850466 | BQ88: 0.033726915 | BR88: 0.0029356803 | BS88: 0.0080297539 | BT88: 1.3931062 | BU88: 0.9922355 | BV88: 0.69103258 | BW88: 0.18388077 | BX88: 0.67550898 | BY88: 0.0011744375 | IM88: 252.52447 | IP88: 14.830329 | IS88: 1.3580574
A89: c-CTL_0 | B89: 0.013242715 | D89: 0.038598491 | E89: 1.5707689 | F89: 0.048378708 | I89: 0.021372914 | J89: 161.86801 | N89: 4.0246823 | O89: 0.14444599 | P89: 0.0029129424 | Q89: 11.45491 | R89: 24.913093 | S89: 3.5317924 | T89: 469.17448 | U89: 0.41720572 | V89: 0.028566129 | W89: 1.2211935 | X89: 0.0026787751 | Y89: 4.7132214 | Z89: 1.7821018 | AA89: 0.43241315 | AD89: 0.93270445 | AE89: 6.5623956 | AF89: 3.9688157 | AH89: 2.901534 | AI89: 0.83657725 | AJ89: 0.15991809 | AL89: 0.68934322 | AM89: 1.8513177 | AN89: 5.4224424 | AO89: 0.011105654 | AP89: 0.0094000687 | AQ89: 0.015714215 | AR89: 0.022625906 | AS89: 0.0082476849 | AT89: 0.1869529 | BI89: 11.62178 | BJ89: 59.043555 | BK89: 37.959828 | BL89: 52.823798 | BM89: 6.2034441 | BN89: 6.4739997 | BO89: 14.599274 | BP89: 95.612643 | BQ89: 0.24291119 | BR89: 0.016559721 | BS89: 0.053742951 | BT89: 4.1053519 | BU89: 0.026390222 | BV89: 4.267215 | BW89: 2.1321662 | BX89: 3.8005024 | BY89: 0.0039234919 | IM89: 2810.5374 | IN89: 41.799962 | IP89: 183.59431 | IS89: 0.07214958
A90: c-OAP_0 | B90: 0.00031636059 | F90: 0.0027722217 | I90: 0.00046344658 | K90: 0.12662251 | N90: 2.4738385 | O90: 0.088955084 | P90: 0.0014700562 | Q90: 7.8636353 | R90: 16.514566 | S90: 2.1687976 | T90: 0.21255221 | U90: 152.73508 | V90: 0.02588933 | W90: 0.32875311 | X90: 0.0022113973 | Y90: 4.4542964 | Z90: 1.2235886 | AA90: 0.36833791 | AD90: 0.64032336 | AE90: 4.3603552 | AF90: 2.136087 | AH90: 2.0090249 | AI90: 0.31542911 | AL90: 0.14013393 | AM90: 0.37483475 | AN90: 4.5076801 | AT90: 0.12115189 | BI90: 7.2055122 | BJ90: 36.203016 | BK90: 22.917099 | BL90: 25.742778 | BM90: 3.0896469 | BN90: 3.155424 | BO90: 33.189153 | BP90: 49.973218 | BQ90: 0.060635847 | BR90: 0.010339525 | BS90: 0.0042076397 | BT90: 2.550309 | BU90: 0.060955108 | BV90: 2.1791262 | BX90: 3.6266371 | BY90: 0.0009187055 | IM90: 659.15101 | IN90: 9.5138537 | IP90: 41.579656 | IS90: 0.82625843
A91: c-RMK_0 | B91: 0.0027591256 | F91: 0.0036136364 | I91: 0.00041766142 | L91: 3.600807 | N91: 0.30094473 | O91: 0.010647966 | Q91: 0.95379691 | R91: 1.89247 | S91: 0.26431726 | W91: 493.2573 | Y91: 0.29517411 | AE91: 0.48053861 | AF91: 0.30606545 | AH91: 0.25976774 | BJ91: 4.4100579 | BK91: 2.8091403 | BL91: 3.7907853 | BM91: 0.4447725 | BN91: 0.46453468 | BO91: 1.046893 | BP91: 7.479209 | BQ91: 0.26125442 | BR91: 0.038938156 | BS91: 0.028704342 | BT91: 0.17534725 | BV91: 0.40299747 | BW91: 0.078600987 | BX91: 0.26673665 | IM91: 208.82502 | IP91: 13.164725 | IS91: 0.0052811525
A92: c-WOL_0 | M92: 2.3261907 | N92: 0.05371844 | O92: 0.0019355913 | S92: 0.047161232 | Y92: 0.052954609 | AB92: 0.0052749645 | AE92: 0.083553601 | AI92: 0.024251419 | BJ92: 0.78700653 | BK92: 0.49772624 | BL92: 0.70524789 | BM92: 0.082883562 | BO92: 0.19434773 | BP92: 1.2676401 | BT92: 0.056037405 | IM92: 101.61156 | IS92: 0.33418101
A93: c-FRS_0 | B93: 0.0048835053 | C93: 1.1733535 | D93: 0.35486062 | E93: 9.721364 | F93: 0.11206156 | I93: 0.0074068607 | J93: 2.878267 | K93: 0.32885416 | L93: 0.51625585 | M93: 0.14117579 | N93: 2.5387506 | P93: 0.0013363426 | S93: 0.5780271 | T93: 3.4154342 | U93: 2.3820166 | V93: 1.8619402 | W93: 5.304943 | X93: 0.056802023 | Y93: 0.37454101 | Z93: 52.585797 | AA93: 30.549449 | AE93: 5.6283801 | AF93: 0.28499661 | AH93: 0.55837972 | AI93: 0.073437881 | AL93: 0.080628054 | AN93: 1.12297 | AT93: 0.02884484 | BI93: 4.5756504 | BJ93: 9.5055694 | BK93: 5.928349 | BL93: 12.80107 | BM93: 3.976198 | BN93: 0.73101241 | BO93: 3.4693349 | BP93: 5.443705 | BQ93: 0.12462597 | BR93: 0.026321197 | BS93: 0.010831118 | BT93: 0.60516078 | BU93: 0.018501318 | BV93: 0.61792337 | BX93: 0.8789726 | IM93: 525.93433 | IN93: 11.354816 | IP93: 32.898146 | IS93: 0.078229858
A94: c-FSH_0 | N94: 0.02721076 | O94: 0.14896991 | U94: 0.061768919 | W94: 0.76900172 | X94: 0.0017733241 | Z94: 4.202737 | AA94: 0.26834186 | BK94: 3.1361957 | BX94: 0.69427131 | BY94: 0.00083136231 | IM94: 20.345875 | IS94: 8.6398673
A95: c-COA_0 | P95: 6.7813565 | AU95: 0.038368662 | BI95: 3.4396385 | BM95: 0.056981394 | IS95: 0.072130113
A96: c-OIL_0 | P96: 0.23371652 | Q96: 11.248479 | R96: 0.84680152 | AG96: 8332.4469 | BE96: 0.048185656 | BI96: 1.9537124 | BL96: 0.81568226 | BO96: 0.14798427 | BP96: 0.33542358 | IS96: 10237.537
A97: c-GAS_0 | B97: 0.0087401552 | C97: 1.8756878 | D97: 0.59439649 | E97: 13.060448 | F97: 0.1867338 | I97: 0.0059444808 | J97: 0.17389993 | K97: 0.057728764 | L97: 0.038915441 | M97: 0.014449975 | N97: 1.1309858 | P97: 0.15100344 | Q97: 0.54421958 | R97: 41.300275 | S97: 0.60413108 | T97: 0.46800026 | U97: 2.1951524 | V97: 4.394017 | W97: 18.63192 | X97: 0.14239618 | Y97: 0.056981917 | Z97: 58.143955 | AA97: 4.7436425 | AB97: 0.0409419 | AF97: 0.23031032 | AG97: 6508.0201 | AH97: 356.93022 | AI97: 25.13945 | AJ97: 151.9623 | AK97: 30.721141 | AL97: 9.1339863 | AS97: 0.0066025601 | AT97: 0.27010849 | AX97: 353.27794 | BC97: 154.95526 | BG97: 0.37146665 | BH97: 0.33520525 | BI97: 465.1764 | BJ97: 49.096847 | BK97: 0.12167063 | BL97: 283.64071 | BM97: 4.6137602 | BN97: 4.9820763 | BO97: 34.595581 | BP97: 107.34045 | BQ97: 1.0302203 | BR97: 0.028853037 | BS97: 0.28356674 | BT97: 1.9282918 | BV97: 0.97080065 | BW97: 0.45557297 | BX97: 1.4766077 | IM97: 2081.9133 | IS97: 28976.345
A98: c-OXT_0 | B98: 0.00068529056 | C98: 0.15338689 | D98: 0.061689399 | E98: 1.3381858 | F98: 0.017943213 | I98: 0.001299546 | J98: 0.35859679 | L98: 0.063145756 | M98: 0.021583425 | N98: 0.089059609 | O98: 0.001791776 | P98: 0.003331901 | Q98: 6.3647163 | R98: 4.3580623 | S98: 1.4930798 | X98: 0.00046110212 | Z98: 0.45841388 | AA98: 0.26931966 | AF98: 0.097645475 | AH98: 8.1020012 | AJ98: 0.20313119 | AK98: 80.409847 | AL98: 14.061361 | AM98: 91.262859 | AN98: 3.9385378 | AO98: 0.00738556 | AP98: 0.0052169387 | AQ98: 0.012683726 | AT98: 0.027289712 | BH98: 0.084002934 | BI98: 594.79041 | BJ98: 0.45845997 | BS98: 0.0045441762 | BT98: 0.10621996 | BY98: 0.014824822 | IS98: 88.297551
A99: c-CMT_0 | B99: 0.034074152 | C99: 9.5912907 | D99: 1.2451172 | E99: 59.035554 | F99: 0.58507108 | I99: 0.19491479 | J99: 33.888908 | K99: 7.1454092 | L99: 6.6465605 | M99: 1.3110167 | N99: 6.1635457 | O99: 0.18600655 | T99: 2.1931568 | U99: 0.11329189 | W99: 0.078996093 | Z99: 4.6435788 | AD99: 3.6898964 | AH99: 5.9842233 | AI99: 0.51783315 | AL99: 0.17138728 | AN99: 4.2803509 | BI99: 8.5043364 | BJ99: 43.956923 | BK99: 25.703582 | BL99: 1.2280178 | BM99: 2.212912 | BN99: 0.11978528 | BO99: 14.367874 | BP99: 4.3276885 | BU99: 0.037504963 | BV99: 0.2918238 | BW99: 0.20176391 | BX99: 0.91497734 | IM99: 670.64272 | IN99: 10.558615 | IS99: 0.17220171
A100: c-OMT_0 | I100: 0.00039794415 | N100: 0.91957292 | O100: 0.027792958 | U100: 3.0296875 | Z100: 1.7473914 | AD100: 0.29062822 | AH100: 0.91379372 | AI100: 0.064158548 | AN100: 0.65133579 | BJ100: 6.5716699 | BK100: 4.480654 | BM100: 0.37308799 | BO100: 2.8332496 | BX100: 0.27125058 | IM100: 292.05021 | IN100: 4.6277167 | IS100: 0.87326807
...

Sheet Labor
C1: a-PDR_0 | D1: a-WHT_0 | E1: a-GRO_0 | F1: a-V_F_0 | G1: a-OSD_0 | H1: a-C_B_0 | I1: a-PFB_0 | J1: a-OCR_0 | K1: a-CTL_0 | L1: a-OAP_0 | M1: a-RMK_0 | N1: a-WOL_0 | O1: a-FRS_0 | P1: a-FSH_0 | Q1: a-COA_0 | R1: a-OIL_0 | S1: a-GAS_0 | T1: a-OXT_0 | U1: a-CMT_0 | V1: a-OMT_0 | W1: a-VOL_0 | X1: a-MIL_0 | Y1: a-PCR_0 | Z1: a-SGR_0 | AA1: a-OFD_0 | AB1: a-B_T_0 | AC1: a-TEX_0 | AD1: a-WAP_0 | AE1: a-LEA_0 | AF1: a-LUM_0 | AG1: a-PPP_0 | AH1: a-P_C_0 | AI1: a-CHM_0 | AJ1: a-BPH_0 | AK1: a-RPP_0 | AL1: a-NMM_0 | AM1: a-I_S_0 | AN1: a-NFM_0 | AO1: a-FMP_0 | AP1: a-ELE_0 | AQ1: a-EEQ_0 | AR1: a-OME_0 | AS1: a-MVH_0 | AT1: a-OTN_0 | AU1: a-OMF_0 | AV1: a-TnD_0 | AW1: a-GasBL_0 | AX1: a-WindBL_0 | AY1: a-HydroBL_0 | AZ1: a-GasP_0 | BA1: a-OilP_0 | BB1: a-SolarP_0 | BC1: a-GDT_0 | BD1: a-WTR_0 | BE1: a-CNS_0 | BF1: a-TRD_0 | BG1: a-AFS_0 | BH1: a-OTP_0 | BI1: a-WTP_0 | BJ1: a-ATP_0 | BK1: a-WHS_0 | BL1: a-CMN_0 | BM1: a-OFI_0 | BN1: a-INS_0 | BO1: a-RSA_0 | BP1: a-OBS_0 | BQ1: a-ROS_0 | BR1: a-OSG_0 | BS1: a-EDU_0 | BT1: a-HHT_0 | BU1: a-DWE_0 | BV1: a-macc_0
A2: DZA | B2: f-m_skl_0 | C2: 0.02664689 | D2: 2.2601287 | E2: 0.75468649 | F2: 52.101186 | G2: 0.53288457 | H2: 0.00014498568 | I2: 0.0066915987 | J2: 0.064345941 | K2: 15.2501 | L2: 4.2916303 | M2: 2.3776358 | N2: 0.31014125 | O2: 0.6435429 | P2: 0.041564017 | Q2: 0.0096595161 | R2: 34.348476 | S2: 41.570131 | T2: 8.4135921 | U2: 0.24974914 | V2: 0.34265343 | W2: 0.096280176 | X2: 1.0772473 | Y2: 0.0044634951 | Z2: 0.026102453 | AA2: 8.3558391 | AB2: 2.5235319 | AC2: 0.094330924 | AD2: 0.71547775 | AE2: 8.341376 | AF2: 3.6003097 | AG2: 2.2631311 | AH2: 15.462999 | AI2: 1.1856614 | AJ2: 0.19826336 | AK2: 3.4466039 | AL2: 40.459469 | AM2: 0.3326942 | AN2: 1.1354922 | AO2: 26.821311 | AP2: 0.40022091 | AQ2: 0.49239408 | AR2: 1.2358324 | AS2: 0.98051156 | AT2: 0.39311896 | AU2: 0.36866248 | AV2: 11.178578 | AW2: 5.0960006 | AX2: 0.0020304289 | AY2: 0.0090002628 | AZ2: 1.0288362 | BA2: 0.093102374 | BB2: 0.10903465 | BC2: 128.88883 | BD2: 60.92022 | BE2: 247.15233 | BF2: 277.52697 | BG2: 58.713305 | BH2: 56.756664 | BI2: 3.1316166 | BJ2: 0.99780444 | BK2: 19.87288 | BL2: 78.113935 | BM2: 20.609196 | BN2: 1.9519858 | BO2: 5.2114649 | BP2: 71.468192 | BQ2: 2.9579942 | BR2: 190.44566 | BS2: 111.11669 | BT2: 274.32517 | BU2: 0.21001414 | BV2: 9.2536184e-05
A3: DZA | B3: f-f_skl_0 | C3: 0.0060154023 | D3: 0.51334262 | E3: 0.1630466 | F3: 15.386624 | G3: 0.15574008 | H3: 3.836078e-05 | I3: 0.0014432035 | J3: 0.017069211 | K3: 3.5749319 | L3: 0.9999716 | M3: 0.57310913 | N3: 0.076227865 | O3: 0.13611881 | P3: 0.010237566 | Q3: 0.0033528394 | R3: 14.487246 | S3: 17.561852 | T3: 2.3880331 | U3: 0.10426602 | V3: 0.14211571 | W3: 0.036183494 | X3: 0.47928948 | Y3: 0.0019660289 | Z3: 0.010052838 | AA3: 4.004271 | AB3: 0.94710194 | AC3: 0.065502855 | AD3: 0.63523583 | AE3: 4.5125864 | AF3: 1.1613291 | AG3: 0.90946318 | AH3: 4.8919035 | AI3: 0.51251569 | AJ3: 0.093685026 | AK3: 1.1963568 | AL3: 11.215183 | AM3: 0.11446477 | AN3: 0.39426363 | AO3: 7.457471 | AP3: 0.16468166 | AQ3: 0.15309494 | AR3: 0.4618892 | AS3: 0.25659256 | AT3: 0.12205395 | AU3: 0.11862687 | AV3: 8.5001075 | AW3: 3.874961 | AX3: 0.001543923 | AY3: 0.0068437329 | AZ3: 0.78231939 | BA3: 0.070794353 | BB3: 0.082909138 | BC3: 38.249918 | BD3: 16.140466 | BE3: 47.550893 | BF3: 143.7607 | BG3: 39.438158 | BH3: 13.320042 | BI3: 1.3927965 | BJ3: 0.58793429 | BK3: 7.1178795 | BL3: 36.259168 | BM3: 17.000938 | BN3: 1.447872 | BO3: 3.0574077 | BP3: 38.329019 | BQ3: 2.4694101 | BR3: 135.70378 | BS3: 156.2874 | BT3: 382.62004 | BU3: 0.075269907 | BV3: 0.0001121384
A4: DZA | B4: f-m_nsk_0 | C4: 0.89155275 | D4: 75.481145 | E4: 24.852977 | F4: 1812.9267 | G4: 18.233423 | H4: 0.0049094896 | I4: 0.22346759 | J4: 2.2049483 | K4: 520.33207 | L4: 145.02634 | M4: 77.614006 | N4: 10.709214 | O4: 21.642621 | P4: 0.34334432 | Q4: 0.022980893 | R4: 81.678645 | S4: 97.296036 | T4: 18.697172 | U4: 1.5756188 | V4: 2.1508419 | W4: 0.60302248 | X4: 6.888218 | Y4: 0.028497496 | Z4: 0.16549401 | AA4: 55.332245 | AB4: 16.407347 | AC4: 0.6469569 | AD4: 5.3222175 | AE4: 59.667872 | AF4: 22.809491 | AG4: 15.435662 | AH4: 93.171446 | AI4: 7.9901064 | AJ4: 1.2711311 | AK4: 21.721603 | AL4: 310.03197 | AM4: 2.3669564 | AN4: 6.8775762 | AO4: 170.10478 | AP4: 2.6605729 | AQ4: 3.0418701 | AR4: 8.4148579 | AS4: 6.2221511 | AT4: 2.5302757 | AU4: 2.2491534 | AV4: 22.759199 | AW4: 17.922418 | AX4: 0.0054524671 | AY4: 0.031653542 | AZ4: 2.7275627 | BA4: 0.24682507 | BB4: 0.39428871 | BC4: 252.533 | BD4: 119.32409 | BE4: 2747.2221 | BF4: 328.25513 | BG4: 57.700896 | BH4: 170.96475 | BI4: 7.6623819 | BJ4: 3.3863648 | BK4: 45.888239 | BL4: 183.38271 | BM4: 5.592527 | BN4: 0.52058644 | BO4: 2.2024807 | BP4: 27.614594 | BQ4: 22.536369 | BR4: 230.53004 | BS4: 77.915503 | BT4: 363.93358 | BU4: 0.1227119 | BV4: 0.00012418253
A5: DZA | B5: f-f_nsk_0 | C5: 0.10905307 | D5: 9.8717455 | E5: 3.1794307 | F5: 254.94146 | G5: 2.5392915 | H5: 0.00076760525 | I5: 0.030131423 | J5: 0.33560047 | K5: 72.071045 | L5: 22.147789 | M5: 10.862592 | N5: 1.5012567 | O5: 2.540632 | P5: 0.045719235 | Q5: 0.002501999 | R5: 11.506703 | S5: 12.28373 | T5: 1.6490763 | U5: 0.27707219 | V5: 0.38993758 | W5: 0.085702073 | X5: 1.2786745 | Y5: 0.0051379802 | Z5: 0.0257813 | AA5: 11.479584 | AB5: 2.8921634 | AC5: 0.22995225 | AD5: 2.1125089 | AE5: 12.71621 | AF5: 2.502553 | AG5: 2.9000612 | AH5: 13.062229 | AI5: 1.4927508 | AJ5: 0.27901108 | AK5: 2.7333571 | AL5: 34.958249 | AM5: 0.36211535 | AN5: 0.95469899 | AO5: 14.431799 | AP5: 0.55858376 | AQ5: 0.36320692 | AR5: 1.0327964 | AS5: 0.83800232 | AT5: 0.3005391 | AU5: 0.26451997 | AV5: 4.1300827 | AW5: 3.2523583 | AX5: 0.00098945224 | AY5: 0.0057441278 | AZ5: 0.49496731 | BA5: 0.044791031 | BB5: 0.071551068 | BC5: 21.141221 | BD5: 9.2744528 | BE5: 102.35661 | BF5: 71.164391 | BG5: 19.266847 | BH5: 6.0425109 | BI5: 0.55351747 | BJ5: 0.45660713 | BK5: 2.7609084 | BL5: 24.244534 | BM5: 1.6024438 | BN5: 0.12058369 | BO5: 0.37021707 | BP5: 4.8852179 | BQ5: 10.690457 | BR5: 37.578558 | BS5: 30.003028 | BT5: 185.57974 | BU5: 0.021230819 | BV5: 0.00018177154
